[{"conversations": [{"content": "闇龍所見的世界　前篇", "speakerName": "", "type": "conversation"}, {"content": "「再來……就拜託你了，闇龍。以瑪納的形式，繼承吾之靈魂吧。我的契約就到此結束了，再來……就都交給……你的意志了……」", "speakerName": "", "type": "conversation"}, {"content": "半夢半醒的闇龍於午睡深淵所看見的，是映著契約者死亡之姿──的夢境。闇龍醒了之後，仍對那鮮明得彷彿曾經歷過一般的夢，感到膽顫心驚。", "speakerName": "", "type": "conversation"}, {"content": "只是個夢。闇龍之主如今尚健在，並且已是混沌時代中的一縷希望之光。闇龍如此告訴自己。", "speakerName": "", "type": "conversation"}, {"content": "「各位，別喪氣！只要撐過現在就還有希望！」正當闇龍看見主人以王之威嚴鼓舞眾人而感到安心時，下個瞬間，他猛然睜開雙眼。", "speakerName": "", "type": "conversation"}, {"content": "清醒的闇龍面前，站著金髮的少年。稚氣未脫的臉上，掛著不適合他的陰沉表情。「呵呵呵……號稱傳說六龍的龍族也才這種程度嗎……」", "speakerName": "", "type": "conversation"}, {"content": "受壓倒性力量所支配的恐懼襲向了闇龍。他感到自己逐漸不再是自己的絕望，同時，卻也感到被溫柔擁抱般的安心。闇龍的意識緩緩往深處下沉……", "speakerName": "", "type": "conversation"}, {"content": "「啊啊啊啊啊啊啊啊啊啊啊！哥、哥哥大人……對不……起……」闇龍忽然清醒。在他眼前，少女的生命之火正逐漸消逝。而奪走她性命的──正是闇龍自己。", "speakerName": "", "type": "conversation"}, {"content": "是我……親手……！不，不對！這是──夢，只是夢。然而……是否真的是夢……？抑或者，我……我──！", "speakerName": "", "type": "conversation"}, {"content": "闇龍的悲泣消失於深沉的黑暗之中。什麼是夢境，什麼是真實。睜眼所見的是現實嗎，又或者只是尚未脫離的夢境。", "speakerName": "", "type": "conversation"}, {"content": "闇龍的心動搖，他茫然地思考著。是否一切都是闇龍夢中發生的事呢？不，說到底自己真是闇龍嗎？", "speakerName": "", "type": "conversation"}, {"content": "在這分不清夢境與現實，彷彿甜美劇毒般的永劫時光中，闇龍只能被玩弄於鼓掌之間──", "speakerName": "", "type": "conversation"}]}, {"conversations": [{"content": "闇龍所見的世界　後篇", "speakerName": "", "type": "conversation"}, {"content": "闇龍所見的世界，是個連夢境與現實都分不清的世界。難以置信的狀況，像是謊言般的事件。闇龍，只能不斷被命運捉弄……", "speakerName": "", "type": "conversation"}, {"content": "「索狄亞克？你怎麼了？」聽見突然有人向自己搭話，闇龍睜開了眼。", "speakerName": "", "type": "conversation"}, {"content": "「真是稀奇，索狄亞克竟然會打瞌睡。」那是個陽光和煦，天氣晴朗的日子。充滿威嚴與慈愛的主人正對闇龍露出微笑。", "speakerName": "", "type": "conversation"}, {"content": "闇龍為自己太過鬆懈謝罪，對此其主只是豁達地笑了笑。「沒什麼好道歉的。能讓你鬆懈正是和平的證明。儘管好好放鬆便是。」", "speakerName": "", "type": "conversation"}, {"content": "如同主人所說，世界太平無事。而經歷壯年，正要步入老年的主人，其治世可說是堅若磐石，想必阿爾貝利亞還會持續壯大吧。", "speakerName": "", "type": "conversation"}, {"content": "這樣的日子能永遠持續就好了。內心雖如此希望，但眼前這過於平穩的狀況卻又不禁感到虛偽。或許正是因為如此吧，才會看見那樣的夢境──", "speakerName": "", "type": "conversation"}, {"content": "「夢？龍族也會做夢啊。」主人的其中一名孩子詢問。那是第七王子。是名雖然尚有些靠不住，卻聰明伶俐的少年，未來令人期待。", "speakerName": "", "type": "conversation"}, {"content": "「跟愛做夢的你還真相配，乾脆締結契約如何啊？」「咦？我、愛做夢……嗎？」「哎呀，莫非你沒有自覺？就是在說這一點喔。」", "speakerName": "", "type": "conversation"}, {"content": "王子王女們的閒聊引起了一陣笑聲，每個人臉上都掛著笑容。面對如此和平的光景，闇龍腦中有個想法。", "speakerName": "", "type": "conversation"}, {"content": "他想著──這是夢境。", "speakerName": "", "type": "conversation"}, {"content": "闇龍的「現實」並非如此平靜，而是殘酷、嚴峻，無可救藥的世界。正因如此，他心中不禁懷有想永遠被這溫暖世界包覆的念頭。", "speakerName": "", "type": "conversation"}, {"content": "但是，在那無可救藥的世界裡，此刻仍有人在戰鬥著。那人不是別人，正是闇龍之主。闇龍早已決心要與他並肩作戰，無論在何種時代，在哪個世界──", "speakerName": "", "type": "conversation"}, {"content": "「……這就是，我所犯下的罪孽盡頭嗎。」主人的嘆息傳入闇龍耳中。當闇龍掙脫溫暖夢境清醒之後，眼前卻是倒著無數屍骸的淒慘光景。", "speakerName": "", "type": "conversation"}, {"content": "這就是闇龍的現實。但是，這樣就好。他將與主人共同背負一切罪孽，背負眾多絕望，背負僅剩的些許希望，然後不斷往前邁進──", "speakerName": "", "type": "conversation"}, {"content": "這正是，屬於闇龍的現實。", "speakerName": "", "type": "conversation"}]}]