[{"chain": [{"combos": [{"cancelActions": [{"action": -999, "conditions": [], "time": 0.400000006}, {"action": -999, "conditions": [], "time": 0.0}, {"action": -999, "conditions": [], "time": 0.0}, {"action": 0, "conditions": [], "time": 0.533333361}], "cancelToNextSec": 0.400000006, "crisisMod": [0.0], "mods": [3.70000005], "odRate": [1.0], "sp": 5, "utp": 0}, {"cancelActions": [{"action": -999, "conditions": [], "time": 0.633333325}, {"action": -999, "conditions": [], "time": 0.0}, {"action": -999, "conditions": [], "time": 0.0}, {"action": 0, "conditions": [], "time": 0.666666687}], "cancelToNextSec": 0.633333325, "crisisMod": [0.0], "mods": [4.07999992], "odRate": [1.0], "sp": 5, "utp": 0}, {"cancelActions": [{"action": -999, "conditions": [], "time": 0.0}, {"action": -999, "conditions": [], "time": 0.0}, {"action": -999, "conditions": [], "time": 1.26666665}, {"action": 0, "conditions": [], "time": 1.26666665}], "cancelToNextSec": 1.26666665, "crisisMod": [0.0], "mods": [5.17999983], "odRate": [1.0], "sp": 5, "utp": 0}], "conditions": [], "hasCrisis": false, "hasUtp": false}], "chainName": {"cht": "預設", "en": "Default", "jp": "預設"}}]