{"ability": {"coAbility": {"chained": {"description": {"cht": "隊伍全員獲得以下能力。\\n角色如果為{element_owner}屬性，\\n則自身使敵方陷入火燒狀態時，\\n發動【15秒間，風屬性抗性提升8％】增益效果。\\n此效果發動後，10秒間不會再次發動。", "en": "If a team member is attuned to {element_owner}:\\nreduces wind damage taken by them by 8%\\nfor 15 seconds when they successfully burn\\nan enemy. After activating, this ability will not\\nactivate again for 10 seconds.\\nBenefits your whole team.", "jp": "パーティ全員が以下のアビリティを得る。\\nキャラが{element_owner}属性なら敵を火傷状態にしたとき、【15秒間、風属性耐性が8％アップするバフ】が発動。\\nこの効果は発動してから10秒間は発動しない。"}, "iconPath": "Icon_Ability_1080003"}, "global": {"description": {"cht": "隊伍全員的HP提升{value1}％，防禦力提升{value1}％。", "en": "Increases HP by {value1}% and defense by {value1}%.\\nBenefits your whole team.", "jp": "パーティ全員のHPが{value1}％アップし、防御力が{value1}％アップする。"}, "iconPath": "Icon_Ability_1010041"}}, "passive": [{"description": {"cht": "HP全滿時攻擊力提升15％。", "en": "Increases strength by 15% when HP is full.", "jp": "HP満タン時、攻撃力が15％アップする｡"}, "iconPath": "Icon_Ability_1020002"}, {"description": {"cht": "陷入「睡眠」狀態機率下降100％。", "en": "Reduces susceptibility to sleep by 100%.", "jp": "「睡眠」状態になる確率が100％ダウンする｡"}, "iconPath": "Icon_Ability_1030010"}, {"description": {"cht": "【覺醒之炎】疊加3次且SP量條累積3條時，技能「天空」轉換成技能「覺醒天空」。\\n技能「覺醒天空」使用後【覺醒之炎】將會解除，並將SP量條歸零。", "en": "If Aether is used when the user has three\\nstacks of Flames of Awakening, and their\\nskill reservoir is at level three, a variant\\ncalled Awakening Aether will be used\\ninstead. Using Awakening Aether will\\nconsume all three stacks of Flames of Awakening\\nand empty the user's skill reservoir.", "jp": "【覚醒の炎】が3つかつSPゲージが3本のとき、スキル「天空」はスキル「覚醒天空」になる。スキル「覚醒天空」使用後、【覚醒の炎】は解除され、SPゲージは0になる。"}, "iconPath": "Icon_Ability_1010040"}]}, "basic": {"cvEn": {"cht": "Matt Mercer", "en": "Matt Mercer", "jp": "Matt Mercer"}, "cvJp": {"cht": "杉田智和", "en": "Tomokazu Sugita", "jp": "杉田智和"}, "element": 1, "hasUniqueDragon": false, "iconName": "110359_01_r05", "id": 10150105, "name": {"cht": "庫洛武", "en": "Chrom", "jp": "クロム"}, "rarity": 5, "releaseEpoch": 1609480800.0, "weapon": 1}, "skill": {"atkSkills": [{"chara": {"element": 1, "iconName": "110359_01_r05", "id": 10150105, "name": {"cht": "庫洛武", "en": "Chrom", "jp": "クロム"}, "type": 1}, "condition": [], "skill": {"afflictions": [], "buffCountBoost": [{"each": 0, "inEffect": 0, "limit": 0}], "buffZoneBoost": {"ally": 0, "self": 0}, "cancelActionsMax": [{"action": 0, "conditions": [], "time": 1.16666663}], "crisisMax": [0.0], "dispelMax": false, "dispelTimingMax": [], "hitTimingSecMax": [0.6], "hitsMax": 1, "identifiers": ["s1_0s"], "internalId": 101501051, "modsMax": [5.62], "name": {"cht": "聖王之劍", "en": "Exalted Sword", "jp": "聖王の剣"}, "sharable": false, "spGradualPctMax": 0, "spMax": 2304, "ssCost": 0, "ssSp": 0}, "uniqueHash": "1576e8657fca209c9e2c9950002239f84ab9af8e26f46c5b1bafbdd839db2f68"}, {"chara": {"element": 1, "iconName": "110359_01_r05", "id": 10150105, "name": {"cht": "庫洛武", "en": "Chrom", "jp": "クロム"}, "type": 1}, "condition": [], "skill": {"afflictions": [], "buffCountBoost": [{"each": 0, "inEffect": 0, "limit": 0}, {"each": 0, "inEffect": 0, "limit": 0}], "buffZoneBoost": {"ally": 0, "self": 0}, "cancelActionsMax": [{"action": 0, "conditions": [], "time": 2.66666675}], "crisisMax": [0.0, 0.0], "dispelMax": false, "dispelTimingMax": [], "hitTimingSecMax": [1.33333337, 1.83333337], "hitsMax": 2, "identifiers": ["s2_1s_1g", "s2_1s_2g", "s2_1s_3g"], "internalId": 101501052, "modsMax": [1.43, 1.49], "name": {"cht": "天空", "en": "Aether", "jp": "天空"}, "sharable": false, "spGradualPctMax": 0, "spMax": 2650, "ssCost": 0, "ssSp": 0}, "uniqueHash": "949d9d6342e7ba02e521a0bd5b9d83cb6e5c1775f9693d9d56184cb8251daf44"}, {"chara": {"element": 1, "iconName": "110359_01_r05", "id": 10150105, "name": {"cht": "庫洛武", "en": "Chrom", "jp": "クロム"}, "type": 1}, "condition": [191], "skill": {"afflictions": [], "buffCountBoost": [{"each": 0, "inEffect": 0, "limit": 0}, {"each": 0, "inEffect": 0, "limit": 0}], "buffZoneBoost": {"ally": 0, "self": 0}, "cancelActionsMax": [{"action": 0, "conditions": [], "time": 2.66666675}], "crisisMax": [0.0, 0.0], "dispelMax": false, "dispelTimingMax": [], "hitTimingSecMax": [1.33333337, 1.83333337], "hitsMax": 2, "identifiers": ["s2_1s_1g", "s2_1s_2g", "s2_1s_3g"], "internalId": 101501052, "modsMax": [1.716, 1.788], "name": {"cht": "天空", "en": "Aether", "jp": "天空"}, "sharable": false, "spGradualPctMax": 0, "spMax": 2650, "ssCost": 0, "ssSp": 0}, "uniqueHash": "f10f4d18f38266f59fa2be3523afb1ad3a479223693a93379bdf1f53585110fb"}, {"chara": {"element": 1, "iconName": "110359_01_r05", "id": 10150105, "name": {"cht": "庫洛武", "en": "Chrom", "jp": "クロム"}, "type": 1}, "condition": [], "skill": {"afflictions": [], "buffCountBoost": [{"each": 0, "inEffect": 0, "limit": 0}, {"each": 0, "inEffect": 0, "limit": 0}], "buffZoneBoost": {"ally": 0, "self": 0}, "cancelActionsMax": [{"action": 0, "conditions": [], "time": 2.66666675}], "crisisMax": [0.0, 0.0], "dispelMax": false, "dispelTimingMax": [], "hitTimingSecMax": [1.33333337, 1.83333337], "hitsMax": 2, "identifiers": ["s2_2s_1g", "s2_2s_2g", "s2_2s_3g"], "internalId": 101501053, "modsMax": [2.93, 3.58], "name": {"cht": "天空", "en": "Aether", "jp": "天空"}, "sharable": false, "spGradualPctMax": 0, "spMax": 2650, "ssCost": 0, "ssSp": 0}, "uniqueHash": "00d070ce0d74c2c3fe9bf007ec6f4e6356158b7d72955780251e2cc6788f9948"}, {"chara": {"element": 1, "iconName": "110359_01_r05", "id": 10150105, "name": {"cht": "庫洛武", "en": "Chrom", "jp": "クロム"}, "type": 1}, "condition": [191], "skill": {"afflictions": [], "buffCountBoost": [{"each": 0, "inEffect": 0, "limit": 0}, {"each": 0, "inEffect": 0, "limit": 0}], "buffZoneBoost": {"ally": 0, "self": 0}, "cancelActionsMax": [{"action": 0, "conditions": [], "time": 2.66666675}], "crisisMax": [0.0, 0.0], "dispelMax": false, "dispelTimingMax": [], "hitTimingSecMax": [1.33333337, 1.83333337], "hitsMax": 2, "identifiers": ["s2_2s_1g", "s2_2s_2g", "s2_2s_3g"], "internalId": 101501053, "modsMax": [3.516, 4.296], "name": {"cht": "天空", "en": "Aether", "jp": "天空"}, "sharable": false, "spGradualPctMax": 0, "spMax": 2650, "ssCost": 0, "ssSp": 0}, "uniqueHash": "40372a538043296b0628430eacac0795c81648ac042d95ee5c08b484a1cc1c8e"}, {"chara": {"element": 1, "iconName": "110359_01_r05", "id": 10150105, "name": {"cht": "庫洛武", "en": "Chrom", "jp": "クロム"}, "type": 1}, "condition": [], "skill": {"afflictions": [], "buffCountBoost": [{"each": 0, "inEffect": 0, "limit": 0}, {"each": 0, "inEffect": 0, "limit": 0}], "buffZoneBoost": {"ally": 0, "self": 0}, "cancelActionsMax": [{"action": 0, "conditions": [], "time": 2.66666675}], "crisisMax": [0.0, 0.0], "dispelMax": false, "dispelTimingMax": [], "hitTimingSecMax": [1.33333337, 1.85185194], "hitsMax": 2, "identifiers": ["s2_3s_1g", "s2_3s_2g"], "internalId": 101501054, "modsMax": [7.2, 8.01], "name": {"cht": "天空", "en": "Aether", "jp": "天空"}, "sharable": false, "spGradualPctMax": 0, "spMax": 2650, "ssCost": 0, "ssSp": 0}, "uniqueHash": "d408c152f804d5849804557c2c0157fa328d11777e4a29730a9378875f4a3127"}, {"chara": {"element": 1, "iconName": "110359_01_r05", "id": 10150105, "name": {"cht": "庫洛武", "en": "Chrom", "jp": "クロム"}, "type": 1}, "condition": [191], "skill": {"afflictions": [], "buffCountBoost": [{"each": 0, "inEffect": 0, "limit": 0}, {"each": 0, "inEffect": 0, "limit": 0}], "buffZoneBoost": {"ally": 0, "self": 0}, "cancelActionsMax": [{"action": 0, "conditions": [], "time": 2.66666675}], "crisisMax": [0.0, 0.0], "dispelMax": false, "dispelTimingMax": [], "hitTimingSecMax": [1.33333337, 1.85185194], "hitsMax": 2, "identifiers": ["s2_3s_1g", "s2_3s_2g"], "internalId": 101501054, "modsMax": [8.64, 9.612], "name": {"cht": "天空", "en": "Aether", "jp": "天空"}, "sharable": false, "spGradualPctMax": 0, "spMax": 2650, "ssCost": 0, "ssSp": 0}, "uniqueHash": "2c113fd6a682d682f210b1f089bdc49873d3aa80182956dd091f7e869bae71aa"}, {"chara": {"element": 1, "iconName": "110359_01_r05", "id": 10150105, "name": {"cht": "庫洛武", "en": "Chrom", "jp": "クロム"}, "type": 1}, "condition": [], "skill": {"afflictions": [], "buffCountBoost": [{"each": 0, "inEffect": 0, "limit": 0}, {"each": 0, "inEffect": 0, "limit": 0}], "buffZoneBoost": {"ally": 0, "self": 0}, "cancelActionsMax": [{"action": 0, "conditions": [], "time": 2.66666675}], "crisisMax": [0.0, 0.0], "dispelMax": false, "dispelTimingMax": [], "hitTimingSecMax": [1.33333337, 1.81481481], "hitsMax": 2, "identifiers": ["s2_3s_3g"], "internalId": 101501055, "modsMax": [25.55, 26.31], "name": {"cht": "覺醒天空", "en": "Awakening Aether", "jp": "覚醒天空"}, "sharable": false, "spGradualPctMax": 0, "spMax": 7950, "ssCost": 0, "ssSp": 0}, "uniqueHash": "840113d581c416cb632f2481b1bfa7dfe91e07dca49e83f5e6f15414ba401cf7"}, {"chara": {"element": 1, "iconName": "110359_01_r05", "id": 10150105, "name": {"cht": "庫洛武", "en": "Chrom", "jp": "クロム"}, "type": 1}, "condition": [191], "skill": {"afflictions": [], "buffCountBoost": [{"each": 0, "inEffect": 0, "limit": 0}, {"each": 0, "inEffect": 0, "limit": 0}], "buffZoneBoost": {"ally": 0, "self": 0}, "cancelActionsMax": [{"action": 0, "conditions": [], "time": 2.66666675}], "crisisMax": [0.0, 0.0], "dispelMax": false, "dispelTimingMax": [], "hitTimingSecMax": [1.33333337, 1.81481481], "hitsMax": 2, "identifiers": ["s2_3s_3g"], "internalId": 101501055, "modsMax": [30.66, 31.571999999999996], "name": {"cht": "覺醒天空", "en": "Awakening Aether", "jp": "覚醒天空"}, "sharable": false, "spGradualPctMax": 0, "spMax": 7950, "ssCost": 0, "ssSp": 0}, "uniqueHash": "7446f52e892461083f53904a88215a60f3a8ff5980dbfe793c9ff09289c4bb4e"}, {"chara": {"element": 1, "iconName": "110359_01_r05", "id": 10150105, "name": {"cht": "庫洛武", "en": "Chrom", "jp": "クロム"}, "type": 1}, "condition": [], "skill": {"afflictions": [], "buffCountBoost": [{"each": 0, "inEffect": 0, "limit": 0}], "buffZoneBoost": {"ally": 0, "self": 0}, "cancelActionsMax": [{"action": 0, "conditions": [], "time": 1.16666663}], "crisisMax": [0.0], "dispelMax": false, "dispelTimingMax": [], "hitTimingSecMax": [0.6], "hitsMax": 1, "identifiers": ["s1_1s"], "internalId": 101501056, "modsMax": [5.62], "name": {"cht": "聖王之劍", "en": "Exalted Sword", "jp": "聖王の剣"}, "sharable": false, "spGradualPctMax": 0, "spMax": 2304, "ssCost": 0, "ssSp": 0}, "uniqueHash": "bd865137a3110a2520397ff32d71b0f11680d109b37c019cd0d05c09bd23a626"}, {"chara": {"element": 1, "iconName": "110359_01_r05", "id": 10150105, "name": {"cht": "庫洛武", "en": "Chrom", "jp": "クロム"}, "type": 1}, "condition": [], "skill": {"afflictions": [], "buffCountBoost": [{"each": 0, "inEffect": 0, "limit": 0}], "buffZoneBoost": {"ally": 0, "self": 0}, "cancelActionsMax": [{"action": 0, "conditions": [], "time": 1.16666663}], "crisisMax": [0.0], "dispelMax": false, "dispelTimingMax": [], "hitTimingSecMax": [0.6], "hitsMax": 1, "identifiers": ["s1_2s", "s1_3s"], "internalId": 101501057, "modsMax": [5.62], "name": {"cht": "聖王之劍", "en": "Exalted Sword", "jp": "聖王の剣"}, "sharable": false, "spGradualPctMax": 0, "spMax": 2304, "ssCost": 0, "ssSp": 0}, "uniqueHash": "b9a35a74e419610ac95796848d0533912c3bff5d0156c1d01bf60f26c05e2b73"}], "official": [{"description": {"cht": "給予前方敵人火屬性傷害，\\n給予自身【覺醒之炎】。\\n【覺醒之炎】可疊加3次，並依階段強化技能「天空」。\\n【覺醒之炎】狀態中使用技能「天空」時就會解除。", "en": "Deals flame damage to enemies directly ahead,\\nand grants the user one stack of\\nFlames of Awakening. Flames of Awakening\\ncan stack up to three times, and each stack\\nwill progressively increase the strength of\\nAether. Using Aether will consume all stacks\\nof Flames of Awakening.", "jp": "前方の敵に火属性のダメージを与え、自身に【覚醒の炎】を付与する。【覚醒の炎】は3段階まで重複可能で、スキル「天空」を段階に応じて強化する。【覚醒の炎】はスキル「天空」使用時に解除される。"}, "iconPath": "Icon_Skill_102", "name": {"cht": "聖王之劍", "en": "Exalted Sword", "jp": "聖王の剣"}}, {"description": {"cht": "給予目標和其周圍敵人火屬性傷害，\\n對陷入「異常狀態」的敵人傷害上升。\\n並回復所給予的傷害3％份量的自身HP。\\n此回復效果的最大值為自身最大HP的15％。\\n依【覺醒之炎】的階段強化技能「天空」。\\n發動技能「天空」將消費所有的【覺醒之炎】及1條SP量條。", "en": "Deals flame damage to the target and nearby enemies,\\nand restores 3% of the damage inflicted as HP\\nto the user. This recovery caps at 15% of their\\nmaximum HP. Afflicted foes take extra damage. \\nThis skill's strength will increase relative to the\\nnumber of Flames of Awakening stacks the\\nuser has, and will consume all\\nFlames of Awakening stacks and one level\\nof the user's skill reservoir on use.", "jp": "ターゲットとその周囲の敵に火属性のダメージを与える。「状態異常」状態の敵にはダメージがアップする。さらに、与えたダメージの3％分自身のHPを回復する。この回復効果の最大値は自身の最大HPの15％となる。【覚醒の炎】の段階に応じてスキル「天空」は強化される。スキル「天空」の発動に、すべての【覚醒の炎】とSPゲージ1本を消費する。"}, "iconPath": "Icon_Skill_103", "name": {"cht": "天空", "en": "Aether", "jp": "天空"}}]}, "type": 1}