[{"conversations": [{"content": "...Hah!", "speakerName": "Zace", "type": "conversation"}, {"content": "Hot damn! Ya took that fiend down in one strike! Those are some skills ya got, Zace.", "speakerName": "Ranzal", "type": "conversation"}, {"content": "......", "speakerName": "Zace", "type": "conversation"}, {"content": "C'mon, say somethin'. Yer startin' to weird me out over here.", "speakerName": "Ranzal", "type": "conversation"}, {"content": "...Ah. Right.", "speakerName": "Zace", "type": "conversation"}, {"content": "Huh. Man'a few words, I guess.", "speakerName": "Ranzal", "type": "conversation"}, {"content": "...My apologies.", "speakerName": "Zace", "type": "conversation"}, {"content": "Er, ya don't need to apologize for it.", "speakerName": "Ranzal", "type": "conversation"}, {"content": "Ranzal's just worried about you, Zace. He's afraid you might be having a hard time fitting in.", "speakerName": "Euden", "type": "conversation"}, {"content": "I see. Sorry to trouble you.", "speakerName": "Zace", "type": "conversation"}, {"content": "Aw, I'm just bein' nosy. Not every day we pick up an ally as dependable as you, after all.", "speakerName": "Ranzal", "type": "conversation"}, {"content": "Back in my merc days, I had my share of tangles with the Azm Tribe. I know their strength real well.", "speakerName": "Ranzal", "type": "conversation"}, {"content": "What's the Azm Tribe?", "speakerName": "Euden", "type": "conversation"}, {"content": "A group of hunters that live waaay far from here. They're known for makin' tools and whatnot out'a animal bones.", "speakerName": "Ranzal", "type": "conversation"}, {"content": "And is that why Zace wears armor made from bones?", "speakerName": "Euden", "type": "conversation"}, {"content": "......", "speakerName": "Zace", "type": "conversation"}, {"content": "Hey, if the guy keeps fightin' like this, he can wear an outfit made of tin cans far as I'm concerned.", "speakerName": "Ranzal", "type": "conversation"}, {"content": "And on that note, let's get goin', Zace. We'll celebrate our victory with some grub!", "speakerName": "Ranzal", "type": "conversation"}, {"type": "break"}, {"content": "BWAAA HAR HAR HAR!", "speakerName": "???", "type": "conversation"}, {"content": "Heh. Sounds like somebody's happy to be here.", "speakerName": "Ranzal", "type": "conversation"}, {"content": "Feast yer eyes on that gigantic skull, boys! Them fangs're right scary, ain't they?!", "speakerName": "Hunter A", "type": "conversation"}, {"content": "Eeek! P-please stop.", "speakerName": "Staff", "type": "conversation"}, {"content": "C'mon! Ya really gonna give us attitude after we went to the trouble of takin' down a huge beastie like that?", "speakerName": "Hunter B", "type": "conversation"}, {"content": "This varmint mighta attacked the village! You oughta be thankin' us for our service!", "speakerName": "Hunter C", "type": "conversation"}, {"content": "O-oh, I'm quite grateful! Really I am! I just don't especially want bones shoved in my face like this...", "speakerName": "Staff", "type": "conversation"}, {"content": "Like you'da believed us if we didn't show ya! Now go on—give it a real good look!", "speakerName": "Hunter A", "type": "conversation"}, {"content": "Noooo! EEEEEK!", "speakerName": "Staff", "type": "conversation"}, {"content": "BWAAAA HAR HAR HAR!", "speakerName": "Hunters", "type": "conversation"}, {"content": "What a bunch of creeps. I'm gonna go—", "speakerName": "Ranzal", "type": "conversation"}, {"content": "It is shocking how you people have such brazen, unearned confidence despite your every word being utter nonsense.", "speakerName": "Zace", "type": "conversation"}, {"content": "Uh, Zace? What are you—", "speakerName": "Euden", "type": "conversation"}, {"content": "Who the hell are you, bone boy?!", "speakerName": "Hunters", "type": "conversation"}, {"content": "That skull comes from a species of hippopotamus called odotamus.", "speakerName": "Zace", "type": "conversation"}, {"content": "Its body may be quite large, but it's a docile creature that feeds only on grass. It's nowhere near the brute you described.", "speakerName": "Zace", "type": "conversation"}, {"content": "Ya got any proof of that, pal?!", "speakerName": "Hunter B", "type": "conversation"}, {"content": "That skull's front teeth are fang-shaped, but the molars have the flat, millstone-like structure characteristic of the odotamus.", "speakerName": "Zace", "type": "conversation"}, {"content": "Uhhh...", "speakerName": "Hunter C", "type": "conversation"}, {"content": "You guys wanted everyone around town to treat ya like a couple of big dogs, yeah? Guess it didn't work out for ya.", "speakerName": "Ranzal", "type": "conversation"}, {"content": "Maybe you oughta scram before ya embarrass yerselves any more.", "speakerName": "Ranzal", "type": "conversation"}, {"content": "D-dammit!", "speakerName": "Hunters", "type": "conversation"}, {"content": "You sure know your animal bones, Zace. Is everyone from the Azm Tribe like that?", "speakerName": "Euden", "type": "conversation"}, {"content": "...Roughly.", "speakerName": "Zace", "type": "conversation"}, {"content": "Sounds about right for a buncha folks what make weapons and armor and everyday goods outta bones.", "speakerName": "Ranzal", "type": "conversation"}, {"content": "...That's not exactly the whole story. I am simply a fan of bones.", "speakerName": "Zace", "type": "conversation"}, {"content": "My hobby of collecting bones is unusual even among the people of my tribe.", "speakerName": "Zace", "type": "conversation"}, {"content": "In fact, I joined you all because I believed it would be a good chance to collect rare fiend bones.", "speakerName": "Zace", "type": "conversation"}, {"content": "Is that right?", "speakerName": "Euden", "type": "conversation"}, {"content": "I'm sorry for not mentioning it. I was worried it might seem distasteful, and so kept the matter to myself.", "speakerName": "Zace", "type": "conversation"}, {"content": "What're you on about, Zace?! Ain't nobody got a problem with it!", "speakerName": "Ranzal", "type": "conversation"}, {"content": "......?", "speakerName": "Zace", "type": "conversation"}, {"content": "He's right. You don't have to keep the things you like a secret.", "speakerName": "Euden", "type": "conversation"}, {"content": "T-truly?", "speakerName": "Zace", "type": "conversation"}, {"content": "Truly. In fact, here's my secret: I love stuffin' my face with food! Pretty sure it blows Cleo's mind on a daily basis.", "speakerName": "Ranzal", "type": "conversation"}, {"content": "Ha ha! You might be right about that. So as you can see, Zace, there's no need to hide your passions with us.", "speakerName": "Euden", "type": "conversation"}, {"content": "I didn't realize... Th-thank you.", "speakerName": "Zace", "type": "conversation"}, {"content": "Wait, is that a smile? I didn't know ya COULD smile! Well, ain't that a first?", "speakerName": "Ranzal", "type": "conversation"}, {"content": "Heh! I guess you're getting used to being with us, huh?", "speakerName": "Euden", "type": "conversation"}, {"content": "I suppose you may be right.", "speakerName": "Zace", "type": "conversation"}]}, {"conversations": [{"content": "Gah! Where'd that blasted fiend run off to? Any luck, Euden?", "speakerName": "Ranzal", "type": "conversation"}, {"content": "No sign of it. But it's lurking in this forest somewhere—I'm sure of it.", "speakerName": "Euden", "type": "conversation"}, {"content": "...Hmm? Something's on the ground. Wait, these are...", "speakerName": "Zace", "type": "conversation"}, {"content": "Zace? What's up?", "speakerName": "Euden", "type": "conversation"}, {"content": "Remarkable! These are the bones of the mighty tiowolf!", "speakerName": "Zace", "type": "conversation"}, {"content": "Er, what's that?", "speakerName": "Euden", "type": "conversation"}, {"content": "A particularly rare breed of wolf. Take a close look here.", "speakerName": "Zace", "type": "conversation"}, {"content": "Such a gorgeous tibia! ...And what's this?! There's a complete carpal bone as well!", "speakerName": "Zace", "type": "conversation"}, {"content": "The tiowolf has an accessory carpal bone that is treated essentially as a sixth digit.", "speakerName": "Zace", "type": "conversation"}, {"content": "And if you look at this bone here, you'll note that the tiowolf, which is able to grasp objects, can actually–", "speakerName": "Zace", "type": "conversation"}, {"content": "Whoa, whoa! Slow down there, professor. We ain't got time for a lecture right now.", "speakerName": "Ranzal", "type": "conversation"}, {"content": "Sorry, Zace, but he's right. We need to track down the fiend and eliminate it.", "speakerName": "Euden", "type": "conversation"}, {"content": "Ah, my apologies. But you need to hear this, at least: I suspect this wolf was attacked by the same fiend we now pursue.", "speakerName": "Zace", "type": "conversation"}, {"content": "What?!", "speakerName": "Ranzal", "type": "conversation"}, {"content": "The tiowolf tops the food chain here. It's highly unlikely one would leave behind bones in this condition if they perished from natural causes.", "speakerName": "Zace", "type": "conversation"}, {"content": "As such, it must have been attacked by some creature that exists OUTSIDE the food chain–a fiend or the like.", "speakerName": "Zace", "type": "conversation"}, {"content": "I see.", "speakerName": "Euden", "type": "conversation"}, {"content": "A tiowolf wouldn't allow something that attacked its pack to escape. It would give pursuit and enact revenge.", "speakerName": "Zace", "type": "conversation"}, {"content": "Therefore, if we follow these footprints, we should eventually come upon the fiend responsible.", "speakerName": "Zace", "type": "conversation"}, {"content": "All right then—let's follow the trail.", "speakerName": "Euden", "type": "conversation"}, {"type": "break"}, {"content": "...Look! Over there!", "speakerName": "Euden", "type": "conversation"}, {"content": "Grrrrrr!", "speakerName": "Fiend", "type": "conversation"}, {"content": "Aw, hell! It already got the wolves!", "speakerName": "Ranzal", "type": "conversation"}, {"content": "Come on, you two. Let's take it out!", "speakerName": "Euden", "type": "conversation"}, {"content": "Right!", "speakerName": "Ranzal & Zace", "type": "conversation"}, {"content": "How ya like them apples, ugly?! Aw yeah, that's how we do it!", "speakerName": "Ranzal", "type": "conversation"}, {"content": "......", "speakerName": "Zace", "type": "conversation"}, {"content": "Hmm? What are you doing, Zace?", "speakerName": "Euden", "type": "conversation"}, {"content": "I wish to give the wolves slain by that fiend a proper burial.", "speakerName": "Zace", "type": "conversation"}, {"content": "Hey, ain't those the bones we found earlier? You're buryin' them too?", "speakerName": "Ranzal", "type": "conversation"}, {"content": "I am.", "speakerName": "Zace", "type": "conversation"}, {"content": "Look, I'm not what ya'd call savvy in, uh, bone-ology, but ain't those valuable?", "speakerName": "Ranzal", "type": "conversation"}, {"content": "Honestly, I do regret giving up such beautiful examples of osseous matter.", "speakerName": "Zace", "type": "conversation"}, {"content": "But these bones belong to the offspring of the wolf killed by that fiend, and I wish for them to be laid to rest together.", "speakerName": "Zace", "type": "conversation"}, {"content": "Oh man, sorry about that rot I was spoutin'. Here, lemme give ya a hand.", "speakerName": "Ranzal", "type": "conversation"}, {"content": "I'd like to help as well.", "speakerName": "Euden", "type": "conversation"}, {"content": "A beautiful creature has beautiful bones.", "speakerName": "Zace", "type": "conversation"}, {"content": "I want to be the kind of person who can grieve over the death of a creature before admiring what it leaves behind.", "speakerName": "Zace", "type": "conversation"}]}, {"conversations": [{"content": "...Hah! ...Yaah! ...Hngh!", "speakerName": "Elisanne", "type": "conversation"}, {"content": "......", "speakerName": "Zace", "type": "conversation"}, {"content": "What's up with Zace? Don't think the guy's blinked once since Elisanne started her daily trainin'.", "speakerName": "Ranzal", "type": "conversation"}, {"content": "Hee hee! Soooomeone's in looooove!", "speakerName": "Notte", "type": "conversation"}, {"content": "Nah, I don't buy that for a second. He don't strike me as the type to be interested in romance.", "speakerName": "Ranzal", "type": "conversation"}, {"content": "And I'm telling you, that's gotta be it! Look at him—can't you see the smoldering gaze of a man in love?", "speakerName": "Notte", "type": "conversation"}, {"content": "What kinda nonsense are ya–", "speakerName": "Ranzal", "type": "conversation"}, {"content": "...Simply beautiful.", "speakerName": "Zace", "type": "conversation"}, {"content": "WHAAAAT?!", "speakerName": "Ranzal & Notte", "type": "conversation"}, {"content": "Hey, uh, Zace? Don't wanna pry or nothin' but did ya just say ＂simply beautiful＂?", "speakerName": "Ranzal", "type": "conversation"}, {"content": "And were you talking about Elisanne?!", "speakerName": "Notte", "type": "conversation"}, {"content": "Ah, yes. She is quite beautiful.", "speakerName": "Zace", "type": "conversation"}, {"content": "SEEEEEE!", "speakerName": "Notte", "type": "conversation"}, {"content": "Zace? In love? With Elisanne? Man, my mind is BLOWN over here.", "speakerName": "Ranzal", "type": "conversation"}, {"content": "Then this sensation...is love?", "speakerName": "Zace", "type": "conversation"}, {"content": "You probably have a real tight feeling deep in your chest, right?!", "speakerName": "Notte", "type": "conversation"}, {"content": "I'm not certain I follow you, but I DO feel moved to the core of my being.", "speakerName": "Zace", "type": "conversation"}, {"content": "Welp, that settles it. It's gotta be love! And that means you should go confess your feelings to her RIGHT NOW!", "speakerName": "Notte", "type": "conversation"}, {"content": "Er, confess my feelings?", "speakerName": "Zace", "type": "conversation"}, {"content": "Ain't no reason to hem and haw about it. I'm with Notte—just get over there and put it all out in the open.", "speakerName": "Ranzal", "type": "conversation"}, {"content": "Put it all out...", "speakerName": "Zace", "type": "conversation"}, {"content": "Don't listen to this idiot, Zace! You can't just waltz over and open your big mouth; you need to set the mood!", "speakerName": "Notte", "type": "conversation"}, {"content": "Nope! In a situation like this, yer best bet is to just get right to the point. ...Oh, hey there, Euden!", "speakerName": "Ranzal", "type": "conversation"}, {"content": "Looks like you're all excited about something. What's going on?", "speakerName": "Euden", "type": "conversation"}, {"content": "Euden, help us out here. Advise Zace in the ways of love.", "speakerName": "Ranzal", "type": "conversation"}, {"content": "Um...", "speakerName": "Euden", "type": "conversation"}, {"content": "Surely you agree that you need a little style when you're talkin' to a lady, right? Not like this big idiot here!", "speakerName": "Notte", "type": "conversation"}, {"content": "I'm...really confused.", "speakerName": "Euden", "type": "conversation"}, {"content": "Also, I'm not sure I'm much of an expert when it comes to love.", "speakerName": "Euden", "type": "conversation"}, {"content": "But if you love someone, it's probably best to just tell them so clearly and honestly.", "speakerName": "Euden", "type": "conversation"}, {"content": "Hmm. Yes, I suppose you're right. ...Very well. I'll tell her how I feel.", "speakerName": "Zace", "type": "conversation"}, {"content": "Go get 'em, tiger! Grrrrawl!", "speakerName": "Ranzal", "type": "conversation"}, {"type": "break"}, {"content": "......", "speakerName": "Zace", "type": "conversation"}, {"content": "...Well? How'd it go?", "speakerName": "Ranzal", "type": "conversation"}, {"content": "I clearly and honestly told her what I think, and she accused me of ＂ghoulishness.＂", "speakerName": "Zace", "type": "conversation"}, {"content": "Daaaaaamn! That's ice cold.", "speakerName": "Notte", "type": "conversation"}, {"content": "Yes, but it also doesn't really sound like Elisanne to crush someone like that.", "speakerName": "Euden", "type": "conversation"}, {"content": "Actually, yeah. I guess not. What exactly did you say to her, Zace?", "speakerName": "Ranzal", "type": "conversation"}, {"content": "As you advised honesty, I simply told her that her bones were lovely.", "speakerName": "Zace", "type": "conversation"}, {"content": "Ya said WHAT?!", "speakerName": "Ranzal", "type": "conversation"}, {"content": "Her...bones?", "speakerName": "Euden", "type": "conversation"}, {"content": "Indeed. Elisanne's skeletal structure is a thing of true beauty.", "speakerName": "Zace", "type": "conversation"}, {"content": "Her scapula and sacral vertebrae? The flow from her shoulders to her back and then to her waist? Simply splendid.", "speakerName": "Zace", "type": "conversation"}, {"content": "Ah, and her radial styloid process? I never dreamed I'd lay eyes on a thing of such utter beauty!", "speakerName": "Zace", "type": "conversation"}, {"content": "Uhhh...yeah.", "speakerName": "Ranzal", "type": "conversation"}, {"content": "That's... Well, it's a little...", "speakerName": "Euden", "type": "conversation"}, {"content": "Oh, that reminds me! Ranzal, you yourself have gorgeous femurs.", "speakerName": "Zace", "type": "conversation"}, {"content": "Leave my femurs outta this!", "speakerName": "Ranzal", "type": "conversation"}, {"content": "And the delicate curve of Notte's coccyx is quite remarkable.", "speakerName": "Zace", "type": "conversation"}, {"content": "Wait, is that my BUTT?! How would you even know what that looks like, creeper?!", "speakerName": "Notte", "type": "conversation"}, {"content": "When one is an expert on bones, clothing is no hindrance.", "speakerName": "Zace", "type": "conversation"}, {"content": "WHAAAT?! Agh, stop looking at meee!", "speakerName": "Notte", "type": "conversation"}, {"content": "Ah! I feel such passion welling up inside me! Could this also be love?!", "speakerName": "Zace", "type": "conversation"}, {"content": "NOOOOOO IT'S NOOOOOOT!", "speakerName": "Notte", "type": "conversation"}]}, {"conversations": [{"content": "Zace!", "speakerName": "???", "type": "conversation"}, {"content": "Vendra! Is that really you? I never would have thought to see you here!", "speakerName": "Zace", "type": "conversation"}, {"content": "It's been a while, Zace. I heard you were staying in this castle, so I came to visit.", "speakerName": "Vendra", "type": "conversation"}, {"content": "Is this an acquaintance of yours, Zace?", "speakerName": "Euden", "type": "conversation"}, {"content": "Ah, you are Euden, yes? I am Vendra, an old friend of Zace's. We were quite close in our youth.", "speakerName": "Vendra", "type": "conversation"}, {"content": "Well, any friend of Zace is welcome here.", "speakerName": "Euden", "type": "conversation"}, {"content": "Rumor has it you became a merchant.", "speakerName": "Zace", "type": "conversation"}, {"content": "I did. And while I don't mean to boast, I've done rather well for myself.", "speakerName": "Vendra", "type": "conversation"}, {"content": "I'm glad to hear of your success.", "speakerName": "Zace", "type": "conversation"}, {"content": "Yes, well, my business may be booming, but I wish I could say the same for my body. I'm quite out of shape these days!", "speakerName": "Vendra", "type": "conversation"}, {"content": "Which is one reason I'm here. I was recalling our youth, and thought we might go hunting together again.", "speakerName": "Vendra", "type": "conversation"}, {"content": "Hunting, you say?", "speakerName": "Zace", "type": "conversation"}, {"content": "He came all this way, so how about it?", "speakerName": "Euden", "type": "conversation"}, {"content": "Yes...I suppose.", "speakerName": "Zace", "type": "conversation"}, {"content": "Would you care to join us, Your Highness? It should be quite enjoyable.", "speakerName": "Vendra", "type": "conversation"}, {"content": "I don't see why not.", "speakerName": "Euden", "type": "conversation"}, {"type": "break"}, {"content": "There!", "speakerName": "Vendra", "type": "conversation"}, {"content": "!!!", "speakerName": "Deer", "type": "conversation"}, {"type": "break"}, {"content": "Yaah!", "speakerName": "Vendra", "type": "conversation"}, {"content": "Cheeep!", "speakerName": "Bird", "type": "conversation"}, {"content": "Aha ha ha! What a haul! The game is plentiful today.", "speakerName": "Vendra", "type": "conversation"}, {"content": "What do you make of that, Zace? Looks like I'm not quite so rusty after all.", "speakerName": "Vendra", "type": "conversation"}, {"content": "The hunters of the Azm Tribe sure do live up to their reputation. Although...", "speakerName": "Euden", "type": "conversation"}, {"content": "Vendra, don't you think this is a bit much? We'll never be able to eat all these animals.", "speakerName": "Zace", "type": "conversation"}, {"content": "Oh, it's fine. We'll just toss out whatever we don't finish.", "speakerName": "Vendra", "type": "conversation"}, {"content": "The purpose of hunting is to live! Throwing away perfectly good game is no different than throwing away a life!", "speakerName": "Zace", "type": "conversation"}, {"content": "How can you think such things and still call yourself an Azm?!", "speakerName": "Zace", "type": "conversation"}, {"content": "I'm no longer with the Azm! I don't have to be bound by those rules!", "speakerName": "Vendra", "type": "conversation"}, {"content": "Be that as it may, I'll not stand here and permit you to commit such a careless waste of life!", "speakerName": "Zace", "type": "conversation"}, {"content": "What kind of high and mighty nonsense has gotten into that head of yours?!", "speakerName": "Vendra", "type": "conversation"}, {"content": "Both of you, calm down! There's no need to be at one another's throats over this!", "speakerName": "Euden", "type": "conversation"}, {"content": "In fact, I've got an idea: Let's go back to the castle and share our catch with everyone.", "speakerName": "Euden", "type": "conversation"}, {"content": "Hmph.", "speakerName": "Zace", "type": "conversation"}, {"content": "Tch.", "speakerName": "Vendra", "type": "conversation"}, {"type": "break"}, {"content": "......", "speakerName": "Zace", "type": "conversation"}, {"content": "...I'm sorry for what happened, Zace. I didn't mean for us to fight.", "speakerName": "Vendra", "type": "conversation"}, {"content": "I apologize for becoming heated myself.", "speakerName": "Zace", "type": "conversation"}, {"content": "I know you've loved bones since we were little, so I brought you something.", "speakerName": "Vendra", "type": "conversation"}, {"content": "These...these are the bones of a jonabird.", "speakerName": "Zace", "type": "conversation"}, {"content": "And what beautiful bones they are! See how the grand wings affix themselves to such a small frame!", "speakerName": "Zace", "type": "conversation"}, {"content": "A sturdy femur, as well as a long radius and ulna that lose none of their beauty even within the heteromorphic structure.", "speakerName": "Zace", "type": "conversation"}, {"content": "A bird so rare it's legendary... I never dreamed I'd see a complete specimen with my own eyes!", "speakerName": "Zace", "type": "conversation"}, {"content": "Th-thank you so much, Vendra.", "speakerName": "Zace", "type": "conversation"}, {"content": "I'm delighted that you like it. Looks like all the coin I spent in order to catch it was well spent.", "speakerName": "Vendra", "type": "conversation"}, {"content": "What...did you say? You captured the bird these bones came from?", "speakerName": "Zace", "type": "conversation"}, {"content": "Yes. Just for you.", "speakerName": "Vendra", "type": "conversation"}, {"content": "...Take them and go. Now.", "speakerName": "Zace", "type": "conversation"}, {"content": "Sorry, what?", "speakerName": "Vendra", "type": "conversation"}, {"content": "Take them and go! I have absolutely no need for bones like these!", "speakerName": "Zace", "type": "conversation"}, {"content": "What're you on about?! I brought them because I thought you'd ENJOY them!", "speakerName": "Vendra", "type": "conversation"}, {"content": "You think I'd be happy that you murdered a living creature?! I'll say this once more: Take them with you and GO!", "speakerName": "Zace", "type": "conversation"}, {"content": "You'd spit on a man's kindness like this? Pah! Consider our friendship over!", "speakerName": "Vendra", "type": "conversation"}, {"content": "...You okay, Zace? That was some fight.", "speakerName": "Euden", "type": "conversation"}, {"content": "I'm sorry you had to see me like that, Euden.", "speakerName": "Zace", "type": "conversation"}, {"content": "You haven't done anything to apologize for. But he was an old friend you hadn't seen in a long time, right?", "speakerName": "Euden", "type": "conversation"}, {"content": "And weren't those bones valuable?", "speakerName": "Euden", "type": "conversation"}, {"content": "Bones are wonderful, but they are still the remnants of living things.", "speakerName": "Zace", "type": "conversation"}, {"content": "In order to collect bones, living creatures must die. ...Sometimes I forget that.", "speakerName": "Zace", "type": "conversation"}, {"content": "That is why I must admonish myself.", "speakerName": "Zace", "type": "conversation"}, {"content": "And also why you...", "speakerName": "Euden", "type": "conversation"}, {"content": "Yes. I don't want anything to die for my own pleasure.", "speakerName": "Zace", "type": "conversation"}]}, {"conversations": [{"content": "You're cornered!", "speakerName": "Zace", "type": "conversation"}, {"content": "GRRRAAAAGH!", "speakerName": "Fiend", "type": "conversation"}, {"content": "You are so focused on Zace, you left yourself wide open. HAAAAH!", "speakerName": "Elisanne", "type": "conversation"}, {"content": "Hmph. A trifle at best.", "speakerName": "Elisanne", "type": "conversation"}, {"content": "GRAAAGH!", "speakerName": "Fiend", "type": "conversation"}, {"content": "Elisanne! Look out!", "speakerName": "Zace", "type": "conversation"}, {"content": "GRAAAAARGH!", "speakerName": "Fiend", "type": "conversation"}, {"content": "Blast! It's still alive!", "speakerName": "Elisanne", "type": "conversation"}, {"content": "Hngh!", "speakerName": "Zace", "type": "conversation"}, {"content": "Zace! ...Curse you, fiend!", "speakerName": "Elisanne", "type": "conversation"}, {"content": "My apologies, Zace. That happened because I was unable to finish it off.", "speakerName": "Elisanne", "type": "conversation"}, {"content": "You're not injured, are you?", "speakerName": "Elisanne", "type": "conversation"}, {"content": "I am unhurt. However, I can't say the same for this...", "speakerName": "Zace", "type": "conversation"}, {"content": "Oh no... Does that mean the sound I heard earlier was the breaking of one of the bones you carry?", "speakerName": "Elisanne", "type": "conversation"}, {"content": "Still, better a carried bone than one of our own, I suppose.", "speakerName": "Elisanne", "type": "conversation"}, {"content": "Yes.", "speakerName": "Zace", "type": "conversation"}, {"type": "break"}, {"content": "......", "speakerName": "Zace", "type": "conversation"}, {"content": "Man, Zace is lookin' even gloomier than usual.", "speakerName": "Ranzal", "type": "conversation"}, {"content": "I wonder if something happened?", "speakerName": "Euden", "type": "conversation"}, {"content": "I fear this is my fault.", "speakerName": "Elisanne", "type": "conversation"}, {"content": "And while I'm not good at brightening people's spirits when they're down, I have to at least make the attempt.", "speakerName": "Elisanne", "type": "conversation"}, {"content": "Zace? I'm...sorry about what happened.", "speakerName": "Elisanne", "type": "conversation"}, {"content": "The bone that got broken, I mean. Er...was it valuable?", "speakerName": "Elisanne", "type": "conversation"}, {"content": "Valuable? No, it was a rather common example that can be found in any human.", "speakerName": "Zace", "type": "conversation"}, {"content": "Wait. It was...human?", "speakerName": "Elisanne", "type": "conversation"}, {"content": "It belonged to my mother—or so I was told. She died when I was a baby.", "speakerName": "Zace", "type": "conversation"}, {"content": "My father pitied me for growing up without her, and so left me that to remember her.", "speakerName": "Zace", "type": "conversation"}, {"content": "Perhaps because I grew up hearing that story, I started to feel as though there was a comforting warmth within it.", "speakerName": "Zace", "type": "conversation"}, {"content": "That may have been what led to me liking bones as much as I do.", "speakerName": "Zace", "type": "conversation"}, {"content": "I had no idea it was so precious!", "speakerName": "Elisanne", "type": "conversation"}, {"content": "Don't trouble yourself over it, Elisanne. It was due to my own inattention.", "speakerName": "Zace", "type": "conversation"}, {"content": "Yet it was so important to you...", "speakerName": "Elisanne", "type": "conversation"}, {"content": "It's all right. What I wanted more than one of my mother's bones...", "speakerName": "Zace", "type": "conversation"}, {"content": "...was for her to be alive.", "speakerName": "Zace", "type": "conversation"}, {"content": "Zace, I'm so sorry.", "speakerName": "Elisanne", "type": "conversation"}, {"content": "I'm happy it was used to save the life of a living person, even if it was destroyed in the process.", "speakerName": "Zace", "type": "conversation"}, {"content": "I see.", "speakerName": "Elisanne", "type": "conversation"}, {"content": "In that case, I am going to make you a promise, Zace.", "speakerName": "Elisanne", "type": "conversation"}, {"content": "You saved me, and because of that, I swear not to let my life go to waste.", "speakerName": "Elisanne", "type": "conversation"}, {"content": "I would like that very much.", "speakerName": "Zace", "type": "conversation"}, {"content": "Still, I can't JUST do that. I must thank you in a more traditional way as well.", "speakerName": "Elisanne", "type": "conversation"}, {"content": "In that case...", "speakerName": "Zace", "type": "conversation"}, {"content": "Did you have something in mind?", "speakerName": "Elisanne", "type": "conversation"}, {"content": "Well, if you were ever to die, Elisanne... Might I have your bones?", "speakerName": "Zace", "type": "conversation"}, {"content": "How did I know we might end up here? But after I die, my bones can–", "speakerName": "Elisanne", "type": "conversation"}, {"content": "Y-you'll give them to me?!", "speakerName": "Zace", "type": "conversation"}, {"content": "I would LIKE to do so, but alas, I am a Paladyn.", "speakerName": "Elisanne", "type": "conversation"}, {"content": "My body must be offered up to the Church. I'm very sorry, but my bones belong to that institution alone.", "speakerName": "Elisanne", "type": "conversation"}, {"content": "I...I see. I suppose that is that.", "speakerName": "Zace", "type": "conversation"}, {"content": "If you think of anything else you might want as thanks, please let me know.", "speakerName": "Elisanne", "type": "conversation"}, {"content": "What she says makes sense. Ah, I suppose I've no choice but to abandon my pursuit of her bones.", "speakerName": "Zace", "type": "conversation"}, {"content": "Wait a moment. Humans have two hundred and six bones in their body...", "speakerName": "Zace", "type": "conversation"}, {"content": "Surely even the Ilian Church would not need QUITE so many...", "speakerName": "Zace", "type": "conversation"}, {"content": "Elisanne, wait!", "speakerName": "Zace", "type": "conversation"}, {"content": "What about just one bone?! Just one would be wonderful!", "speakerName": "Zace", "type": "conversation"}]}]