[{"conversations": [{"audioPaths": ["vo_chr_100001_story/VO_CHR_100001_STORY_0024.wav"], "content": "えーっと……さっきの店で買うものは全部そろったかな。", "isSys": false, "speakerIcon": "story/chara/100001_01.png", "speakerName": "ユーディル", "type": "conversation"}, {"audioPaths": ["vo_chr_100002_story/VO_CHR_100002_STORY_1032.wav"], "content": "はい。では、そろそろ城に戻りましょう――", "isSys": false, "speakerIcon": "story/chara/100002_01.png", "speakerName": "エルフィリス", "type": "conversation"}, {"audioPaths": ["vo_chr_120018_story/VO_CHR_120018_STORY_0056.wav"], "content": "きゃあああっ、ひったくりよー！女性誰か捕まえてー！", "isSys": false, "speakerIcon": "story/chara/120018_01.png", "speakerName": "女性", "type": "conversation"}, {"audioPaths": ["vo_chr_100002_story/VO_CHR_100002_STORY_0002.wav"], "content": "ひったくりだと!?", "isSys": false, "speakerIcon": "story/chara/100002_01.png", "speakerName": "エルフィリス", "type": "conversation"}, {"audioPaths": ["vo_chr_100001_story/VO_CHR_100001_STORY_0052.wav"], "content": "あっちだ、エルフィリス！追うぞ！", "isSys": false, "speakerIcon": "story/chara/100001_01.png", "speakerName": "ユーディル", "type": "conversation"}, {"audioPaths": ["vo_chr_120043_story/VO_CHR_120043_STORY_0004.wav"], "content": "へっ！今さら、遅ぇんだよ！", "isSys": false, "speakerIcon": "story/chara/120043_01.png", "speakerName": "ひったくり", "type": "conversation"}, {"audioPaths": ["vo_chr_100001_story/VO_CHR_100001_STORY_0003.wav"], "content": "なっ……！あいつ、船で逃げる気か!?", "isSys": false, "speakerIcon": "story/chara/100001_01.png", "speakerName": "ユーディル", "type": "conversation"}, {"audioPaths": ["vo_chr_100002_story/VO_CHR_100002_STORY_0075.wav"], "content": "しまった……！川に逃げられては捕まえられない！", "isSys": false, "speakerIcon": "story/chara/100002_01.png", "speakerName": "エルフィリス", "type": "conversation"}, {"audioPaths": ["vo_chr_120043_story/VO_CHR_120043_STORY_0004.wav"], "content": "へへへ！　バカめ！あーばよ……って、ひったくりん？", "isSys": false, "speakerIcon": "story/chara/120043_01.png", "speakerName": "ひったくり", "type": "conversation"}, {"audioPaths": ["vo_chr_100002_story/VO_CHR_100002_STORY_0042.wav"], "content": "えっ……ユーディル、あれを見てください！", "isSys": false, "speakerIcon": "story/chara/100002_01.png", "speakerName": "エルフィリス", "type": "conversation"}, {"audioPaths": ["vo_chr_100001_story/VO_CHR_100001_STORY_1002.wav"], "content": "ひ、人が水面を走ってる!?", "isSys": false, "speakerIcon": "story/chara/100001_01.png", "speakerName": "ユーディル", "type": "conversation"}, {"audioPaths": ["vo_chr_110253_story/VO_CHR_110253_STORY_0053.wav"], "content": "そこのひったくり、ちょっと待ったー！", "isSys": false, "speakerIcon": null, "speakerName": "オルセム", "type": "conversation"}, {"audioPaths": ["vo_chr_100001_story/VO_CHR_100001_STORY_0007.wav"], "content": "え!?と、跳んだ!?", "isSys": false, "speakerIcon": "story/chara/100001_01.png", "speakerName": "ユーディル", "type": "conversation"}, {"audioPaths": ["vo_chr_100002_story/VO_CHR_100002_STORY_0017.wav"], "content": "そのまま回転して……ひったくりの後ろに着地した！", "isSys": false, "speakerIcon": "story/chara/100002_01.png", "speakerName": "エルフィリス", "type": "conversation"}, {"audioPaths": ["vo_chr_110253_story/VO_CHR_110253_STORY_0001.wav"], "content": "よーし、つっかまーえた！", "isSys": false, "speakerIcon": null, "speakerName": "オルセム", "type": "conversation"}, {"audioPaths": ["vo_chr_120043_story/VO_CHR_120043_STORY_0006.wav"], "content": "ぐっ、放せ！なんなんだお前はー！", "isSys": false, "speakerIcon": "story/chara/120043_01.png", "speakerName": "ひったくり", "type": "conversation"}, {"audioPaths": ["vo_chr_110253_story/VO_CHR_110253_STORY_0004.wav"], "content": "オレはオルセム！旅のスケート伝道師さ！", "isSys": false, "speakerIcon": null, "speakerName": "オルセム", "type": "conversation"}, {"audioPaths": ["vo_chr_120043_story/VO_CHR_120043_STORY_0065.wav"], "content": "ひったくり意味わかんねー！放せー！", "isSys": false, "speakerIcon": "story/chara/120043_01.png", "speakerName": "ひったくり", "type": "conversation"}, {"audioPaths": ["vo_chr_110253_story/VO_CHR_110253_STORY_0042.wav"], "content": "意味わかんなくないよ。スケート、楽しいよ？", "isSys": false, "speakerIcon": null, "speakerName": "オルセム", "type": "conversation"}, {"audioPaths": ["vo_chr_110253_story/VO_CHR_110253_STORY_0008.wav"], "content": "でもキミはスケートやる前にあの人に謝らないと。", "isSys": false, "speakerIcon": null, "speakerName": "オルセム", "type": "conversation"}, {"audioPaths": [], "content": "他人のものを無理矢理とっちゃうなんてよくないと思うな。", "isSys": false, "speakerIcon": null, "speakerName": "オルセム", "type": "conversation"}, {"type": "break"}, {"audioPaths": [], "content": "あ、陸に戻ってきた！", "isSys": false, "speakerIcon": "story/chara/100002_01.png", "speakerName": "エルフィリス", "type": "conversation"}, {"audioPaths": ["vo_chr_110253_story/VO_CHR_110253_STORY_0019.wav"], "content": "ちゃんとお役人さんのところで反省するんだよー。", "isSys": false, "speakerIcon": null, "speakerName": "オルセム", "type": "conversation"}, {"audioPaths": ["vo_chr_120043_story/VO_CHR_120043_STORY_0056.wav"], "content": "ひったくり畜生……覚えていやがれ！", "isSys": false, "speakerIcon": "story/chara/120043_01.png", "speakerName": "ひったくり", "type": "conversation"}, {"audioPaths": ["vo_chr_120018_story/VO_CHR_120018_STORY_0005.wav"], "content": "女性荷物を取り返してくれて、ありがとうございました……！", "isSys": false, "speakerIcon": "story/chara/120018_01.png", "speakerName": "女性", "type": "conversation"}, {"audioPaths": ["vo_chr_120019_story/VO_CHR_120019_STORY_0017.wav"], "content": "男性兄ちゃん、かっこいいな！", "isSys": false, "speakerIcon": "story/chara/120019_01.png", "speakerName": "男性", "type": "conversation"}, {"audioPaths": ["vo_chr_120016_story/VO_CHR_120016_STORY_0017.wav"], "content": "お兄ちゃん、お水の上を走れるの？", "isSys": false, "speakerIcon": "story/chara/120016_01.png", "speakerName": "女の子", "type": "conversation"}, {"audioPaths": ["vo_chr_110253_story/VO_CHR_110253_STORY_0004.wav"], "content": "あはは、さっきのは『スケート』って言うんだ！", "isSys": false, "speakerIcon": null, "speakerName": "オルセム", "type": "conversation"}, {"audioPaths": ["vo_chr_110253_story/VO_CHR_110253_STORY_0010.wav"], "content": "スケートは楽しいよ！興味ある人は、オレと滑ろう！", "isSys": false, "speakerIcon": null, "speakerName": "オルセム", "type": "conversation"}, {"audioPaths": ["vo_chr_100001_story/VO_CHR_100001_STORY_0017.wav"], "content": "きみ、すごいな。ところで、スケートってなんなんだ？", "isSys": false, "speakerIcon": "story/chara/100001_01.png", "speakerName": "ユーディル", "type": "conversation"}, {"audioPaths": ["vo_chr_110253_story/VO_CHR_110253_STORY_0042.wav"], "content": "え!?　キミ、スケートに興味ある!?じゃあ、さっそく川へ行こう！", "isSys": false, "speakerIcon": null, "speakerName": "オルセム", "type": "conversation"}, {"audioPaths": ["vo_chr_100001_story/VO_CHR_100001_STORY_0006.wav"], "content": "わ!?　ちょ、急に引っ張られても……って、川にそのまま行くのか!?", "isSys": false, "speakerIcon": "story/chara/100001_01.png", "speakerName": "ユーディル", "type": "conversation"}, {"audioPaths": ["vo_chr_100002_story/VO_CHR_100002_STORY_0053.wav"], "content": "お前！　その手を放せ！殿下の腕を引っ張るなど、無礼だぞ！", "isSys": false, "speakerIcon": "story/chara/100002_01.png", "speakerName": "エルフィリス", "type": "conversation"}, {"audioPaths": ["vo_chr_110253_story/VO_CHR_110253_STORY_0007.wav"], "content": "で、んか……？『でんか』って、王様とかの殿下？", "isSys": false, "speakerIcon": null, "speakerName": "オルセム", "type": "conversation"}, {"audioPaths": ["vo_chr_110253_story/VO_CHR_110253_STORY_0022.wav"], "content": "え!?もしかしてキミ、王様!?", "isSys": false, "speakerIcon": null, "speakerName": "オルセム", "type": "conversation"}, {"audioPaths": ["vo_chr_110253_story/VO_CHR_110253_STORY_0017.wav"], "content": "わぁ……すごいすごい！オレ、王様に初めて会ったよ！", "isSys": false, "speakerIcon": null, "speakerName": "オルセム", "type": "conversation"}, {"audioPaths": [], "content": "ねえねえ！王様なら、スケートを有名にできる!?", "isSys": false, "speakerIcon": null, "speakerName": "オルセム", "type": "conversation"}, {"audioPaths": ["vo_chr_110253_story/VO_CHR_110253_STORY_0012.wav"], "content": "オレ、スケートを世界中に広めるのが夢なんだ！", "isSys": false, "speakerIcon": null, "speakerName": "オルセム", "type": "conversation"}, {"audioPaths": [], "content": "お願い！スケートを有名にしてください！", "isSys": false, "speakerIcon": null, "speakerName": "オルセム", "type": "conversation"}, {"audioPaths": ["vo_chr_100001_story/VO_CHR_100001_STORY_0074.wav"], "content": "え、えっと……おれ、そんなに影響力ないけど……。", "isSys": false, "speakerIcon": "story/chara/100001_01.png", "speakerName": "ユーディル", "type": "conversation"}, {"audioPaths": ["vo_chr_110253_story/VO_CHR_110253_STORY_0031.wav"], "content": "そうだ！　まずはスケートを広めてくれるキミに、その魅力をたくさん伝えないと！", "isSys": false, "speakerIcon": null, "speakerName": "オルセム", "type": "conversation"}, {"audioPaths": [], "content": "ね、キミについて行ってスケートを教えてもいい？　いいよね!?　ね!?", "isSys": false, "speakerIcon": null, "speakerName": "オルセム", "type": "conversation"}, {"audioPaths": ["vo_chr_100001_story/VO_CHR_100001_STORY_0023.wav"], "content": "え、あ、えっと、うん。城に来るくらいなら……。", "isSys": false, "speakerIcon": "story/chara/100001_01.png", "speakerName": "ユーディル", "type": "conversation"}, {"audioPaths": ["vo_chr_110253_story/VO_CHR_110253_STORY_0001.wav"], "content": "やったああああああ！　これでもっとスケートを広められるぞー！", "isSys": false, "speakerIcon": null, "speakerName": "オルセム", "type": "conversation"}, {"audioPaths": ["vo_chr_100002_story/VO_CHR_100002_STORY_0008.wav"], "content": "ユーディル、あの者を城に呼んで、よかったのですか……？", "isSys": false, "speakerIcon": "story/chara/100002_01.png", "speakerName": "エルフィリス", "type": "conversation"}, {"audioPaths": ["vo_chr_100001_story/VO_CHR_100001_STORY_0008.wav"], "content": "ま、まあ、話を聞くくらいならいいんじゃないかな……？", "isSys": false, "speakerIcon": "story/chara/100001_01.png", "speakerName": "ユーディル", "type": "conversation"}], "id": 110253011, "title": "スケート伝道師の大捕物"}, {"conversations": [{"audioPaths": ["vo_chr_100001_story/VO_CHR_100001_STORY_0008.wav"], "content": "オルセムに中庭に呼び出されたけど……なんの用だろう？", "isSys": false, "speakerIcon": "story/chara/100001_01.png", "speakerName": "ユーディル", "type": "conversation"}, {"audioPaths": ["vo_chr_100003_story/VO_CHR_100003_STORY_0011.wav"], "content": "ユーディル、お前も呼ばれたのか。", "isSys": false, "speakerIcon": "story/chara/100003_01.png", "speakerName": "ランザーヴ", "type": "conversation"}, {"audioPaths": ["vo_chr_100001_story/VO_CHR_100001_STORY_0042.wav"], "content": "あれ、ランザーヴもオルセムに？", "isSys": false, "speakerIcon": "story/chara/100001_01.png", "speakerName": "ユーディル", "type": "conversation"}, {"audioPaths": ["vo_chr_100002_story/VO_CHR_100002_STORY_1033.wav"], "content": "ランザーヴだけではありません。", "isSys": false, "speakerIcon": "story/chara/100002_01.png", "speakerName": "エルフィリス", "type": "conversation"}, {"audioPaths": ["vo_chr_100004_story/VO_CHR_100004_STORY_0011.wav"], "content": "私たちもです。", "isSys": false, "speakerIcon": "story/chara/100004_01.png", "speakerName": "クラウ", "type": "conversation"}, {"audioPaths": ["vo_chr_100001_story/VO_CHR_100001_STORY_0060.wav"], "content": "こんなにたくさん集めて、いったい……？", "isSys": false, "speakerIcon": "story/chara/100001_01.png", "speakerName": "ユーディル", "type": "conversation"}, {"audioPaths": ["vo_chr_110253_story/VO_CHR_110253_STORY_0001.wav"], "content": "あ！　みんな！来てくれたんだね！", "isSys": false, "speakerIcon": null, "speakerName": "オルセム", "type": "conversation"}, {"audioPaths": ["vo_chr_100001_story/VO_CHR_100001_STORY_0043.wav"], "content": "オルセム、おれたちを集めてどうしたんだ？", "isSys": false, "speakerIcon": "story/chara/100001_01.png", "speakerName": "ユーディル", "type": "conversation"}, {"audioPaths": ["vo_chr_110253_story/VO_CHR_110253_STORY_0012.wav"], "content": "みんなにスケートのことをもっと知ってもらおうと思ったんだ！", "isSys": false, "speakerIcon": null, "speakerName": "オルセム", "type": "conversation"}, {"audioPaths": ["vo_chr_110253_story/VO_CHR_110253_STORY_0019.wav"], "content": "ということで、じゃじゃーん！スケート講座、はっじまっるよー！", "isSys": false, "speakerIcon": null, "speakerName": "オルセム", "type": "conversation"}, {"audioPaths": ["vo_chr_100002_story/VO_CHR_100002_STORY_0042.wav"], "content": "スケート講座？　確かスケートは氷の上を滑るものだろう？", "isSys": false, "speakerIcon": "story/chara/100002_01.png", "speakerName": "エルフィリス", "type": "conversation"}, {"audioPaths": [], "content": "この中庭には、そんな場所はないように見えるが……。", "isSys": false, "speakerIcon": "story/chara/100002_01.png", "speakerName": "エルフィリス", "type": "conversation"}, {"audioPaths": ["vo_chr_110253_story/VO_CHR_110253_STORY_0040.wav"], "content": "大丈夫、だいじょーぶ！ほら、こうやって……。", "isSys": false, "speakerIcon": null, "speakerName": "オルセム", "type": "conversation"}, {"audioPaths": ["vo_chr_100003_story/VO_CHR_100003_STORY_0042.wav"], "content": "ん？靴になにをつけてんだ？", "isSys": false, "speakerIcon": "story/chara/100003_01.png", "speakerName": "ランザーヴ", "type": "conversation"}, {"audioPaths": ["vo_chr_110253_story/VO_CHR_110253_STORY_0060.wav"], "content": "これはね、スケートのブレード！こうやって靴につけて立てば……", "isSys": false, "speakerIcon": null, "speakerName": "オルセム", "type": "conversation"}, {"audioPaths": ["vo_chr_100001_story/VO_CHR_100001_STORY_0017.wav"], "content": "え!?　オルセムの立ったところが、凍った……!?", "isSys": false, "speakerIcon": "story/chara/100001_01.png", "speakerName": "ユーディル", "type": "conversation"}, {"audioPaths": ["vo_chr_110253_story/VO_CHR_110253_STORY_0004.wav"], "content": "ほらほら！　このブレードをつけるとどこでも氷の道が作れるんだ！", "isSys": false, "speakerIcon": null, "speakerName": "オルセム", "type": "conversation"}, {"audioPaths": ["vo_chr_100001_story/VO_CHR_100001_STORY_0016.wav"], "content": "最初に会ったとき、川を走れたのはこれで凍らせていたからか……。", "isSys": false, "speakerIcon": "story/chara/100001_01.png", "speakerName": "ユーディル", "type": "conversation"}, {"audioPaths": ["vo_chr_110253_story/VO_CHR_110253_STORY_0012.wav"], "content": "このブレードには、氷のマナが封じ込まれてるんだよ。", "isSys": false, "speakerIcon": null, "speakerName": "オルセム", "type": "conversation"}, {"audioPaths": [], "content": "オレの故郷は雪国でね。一族みーんな、氷のマナを使うのが得意なんだ！", "isSys": false, "speakerIcon": null, "speakerName": "オルセム", "type": "conversation"}, {"audioPaths": ["vo_chr_100004_story/VO_CHR_100004_STORY_0016.wav"], "content": "その氷のマナが封じられたブレードならいろんな場所でスケートができますね。", "isSys": false, "speakerIcon": "story/chara/100004_01.png", "speakerName": "クラウ", "type": "conversation"}, {"audioPaths": ["vo_chr_110253_story/VO_CHR_110253_STORY_0031.wav"], "content": "そのとーり！　だから故郷でもスケートはすっごく人気だったんだよ！昔はね。", "isSys": false, "speakerIcon": null, "speakerName": "オルセム", "type": "conversation"}, {"audioPaths": ["vo_chr_100004_story/VO_CHR_100004_STORY_0042.wav"], "content": "昔は？今は違うのですか？", "isSys": false, "speakerIcon": "story/chara/100004_01.png", "speakerName": "クラウ", "type": "conversation"}, {"audioPaths": ["vo_chr_110253_story/VO_CHR_110253_STORY_0038.wav"], "content": "え!?　あ、えっと、それは……。", "isSys": false, "speakerIcon": null, "speakerName": "オルセム", "type": "conversation"}, {"audioPaths": ["vo_chr_110253_story/VO_CHR_110253_STORY_0010.wav"], "content": "そ、そんなことより！　みんなもスケートやってみてよ！　楽しいから！", "isSys": false, "speakerIcon": null, "speakerName": "オルセム", "type": "conversation"}, {"audioPaths": ["vo_chr_100003_story/VO_CHR_100003_STORY_0008.wav"], "content": "でも、俺らはお前みたいなブレードは持ってねぇぞ？", "isSys": false, "speakerIcon": "story/chara/100003_01.png", "speakerName": "ランザーヴ", "type": "conversation"}, {"audioPaths": ["vo_chr_110253_story/VO_CHR_110253_STORY_0007.wav"], "content": "あ、そうだった、そうだった！先にこれを渡さないとね。はい！", "isSys": false, "speakerIcon": null, "speakerName": "オルセム", "type": "conversation"}, {"audioPaths": ["vo_chr_100003_story/VO_CHR_100003_STORY_0060.wav"], "content": "これは、人数分のブレード？", "isSys": false, "speakerIcon": "story/chara/100003_01.png", "speakerName": "ランザーヴ", "type": "conversation"}, {"audioPaths": ["vo_chr_110253_story/VO_CHR_110253_STORY_0073.wav"], "content": "いろんな人にスケートの魅力を知ってほしいからさ。", "isSys": false, "speakerIcon": null, "speakerName": "オルセム", "type": "conversation"}, {"audioPaths": [], "content": "いつでも勧められるように持ち歩いてるんだ。", "isSys": false, "speakerIcon": null, "speakerName": "オルセム", "type": "conversation"}, {"audioPaths": ["vo_chr_100002_story/VO_CHR_100002_STORY_0016.wav"], "content": "用意がいいな……。どうしてそんなにまでして人に勧めるんだ？", "isSys": false, "speakerIcon": "story/chara/100002_01.png", "speakerName": "エルフィリス", "type": "conversation"}, {"audioPaths": ["vo_chr_110253_story/VO_CHR_110253_STORY_0008.wav"], "content": "雪と氷のない場所では、スケートってできないからさ。", "isSys": false, "speakerIcon": null, "speakerName": "オルセム", "type": "conversation"}, {"audioPaths": ["vo_chr_110253_story/VO_CHR_110253_STORY_0023.wav"], "content": "どうしても、あまり人に知られてないんだよね……。", "isSys": false, "speakerIcon": null, "speakerName": "オルセム", "type": "conversation"}, {"audioPaths": ["vo_chr_100001_story/VO_CHR_100001_STORY_0032.wav"], "content": "確かに、おれもきみに会うまでは知らなかったよ。", "isSys": false, "speakerIcon": "story/chara/100001_01.png", "speakerName": "ユーディル", "type": "conversation"}, {"audioPaths": ["vo_chr_110253_story/VO_CHR_110253_STORY_0031.wav"], "content": "そう！　そうなんだよ！そういう人がたくさんいるんだ！", "isSys": false, "speakerIcon": null, "speakerName": "オルセム", "type": "conversation"}, {"audioPaths": [], "content": "すっごくおもしろいのに知らないなんてもったいないでしょ？", "isSys": false, "speakerIcon": null, "speakerName": "オルセム", "type": "conversation"}, {"audioPaths": [], "content": "だったら、オレが知らない人に紹介すればいいじゃんって思ったんだ。", "isSys": false, "speakerIcon": null, "speakerName": "オルセム", "type": "conversation"}, {"audioPaths": ["vo_chr_100001_story/VO_CHR_100001_STORY_0016.wav"], "content": "それで故郷を出て、ひとり各地を旅しているのか。", "isSys": false, "speakerIcon": "story/chara/100001_01.png", "speakerName": "ユーディル", "type": "conversation"}, {"audioPaths": ["vo_chr_100003_story/VO_CHR_100003_STORY_0004.wav"], "content": "はは、なんだかスケートの宣伝大使って感じだな。", "isSys": false, "speakerIcon": "story/chara/100003_01.png", "speakerName": "ランザーヴ", "type": "conversation"}, {"audioPaths": ["vo_chr_110253_story/VO_CHR_110253_STORY_0074.wav"], "content": "へへ、そう？なんだか照れちゃうよ。", "isSys": false, "speakerIcon": null, "speakerName": "オルセム", "type": "conversation"}, {"audioPaths": [], "content": "オレ、キミたちにもスケートを好きになってもらいたいんだ。", "isSys": false, "speakerIcon": null, "speakerName": "オルセム", "type": "conversation"}, {"audioPaths": ["vo_chr_110253_story/VO_CHR_110253_STORY_0019.wav"], "content": "そのためにできることはなんだってする！", "isSys": false, "speakerIcon": null, "speakerName": "オルセム", "type": "conversation"}, {"audioPaths": ["vo_chr_110253_story/VO_CHR_110253_STORY_0040.wav"], "content": "最初は慣れないかもしれないけど、オレが教えるからさ！　やってみない？", "isSys": false, "speakerIcon": null, "speakerName": "オルセム", "type": "conversation"}, {"audioPaths": ["vo_chr_100001_story/VO_CHR_100001_STORY_0012.wav"], "content": "ああ、わかった。オルセム、おれたちにスケートを教えてくれ！", "isSys": false, "speakerIcon": "story/chara/100001_01.png", "speakerName": "ユーディル", "type": "conversation"}, {"audioPaths": ["vo_chr_110253_story/VO_CHR_110253_STORY_0001.wav"], "content": "わーい！じゃあ、さっそく教えるよ。", "isSys": false, "speakerIcon": null, "speakerName": "オルセム", "type": "conversation"}, {"audioPaths": [], "content": "まずは、ブレードをつけた靴で地面に立って……。", "isSys": false, "speakerIcon": null, "speakerName": "オルセム", "type": "conversation"}, {"audioPaths": [], "content": "ガーってやって、バーンっていって、シャーって滑るんだ！ ", "isSys": false, "speakerIcon": null, "speakerName": "オルセム", "type": "conversation"}, {"audioPaths": [], "content": "で、ピョーンで、クルッで、止まるときは、こうギュルギュルって！", "isSys": false, "speakerIcon": null, "speakerName": "オルセム", "type": "conversation"}, {"audioPaths": ["vo_chr_110253_story/VO_CHR_110253_STORY_0019.wav"], "content": "ね？　簡単でしょ？", "isSys": false, "speakerIcon": null, "speakerName": "オルセム", "type": "conversation"}, {"audioPaths": ["vo_chr_100001_story/VO_CHR_100001_STORY_0007.wav"], "content": "え、えっと……。", "isSys": false, "speakerIcon": "story/chara/100001_01.png", "speakerName": "ユーディル", "type": "conversation"}, {"audioPaths": ["vo_chr_100004_story/VO_CHR_100004_STORY_0023.wav"], "content": "宣伝する心意気は認めますが、まずは教え方を磨くところからですね。", "isSys": false, "speakerIcon": "story/chara/100004_01.png", "speakerName": "クラウ", "type": "conversation"}], "id": 110253012, "title": "スケート伝道師の宣伝活動"}, {"conversations": [{"audioPaths": ["vo_chr_110253_story/VO_CHR_110253_STORY_0071.wav"], "content": "さーてと、魔獣はどっこかなー？", "isSys": false, "speakerIcon": "story/chara/110253_01.png", "speakerName": "オルセム", "type": "conversation"}, {"audioPaths": ["vo_chr_100001_story/VO_CHR_100001_STORY_0039.wav"], "content": "オルセム、魔獣退治を手伝ってくれるのはありがたいけど、大丈夫か？", "isSys": false, "speakerIcon": "story/chara/100001_01.png", "speakerName": "ユーディル", "type": "conversation"}, {"audioPaths": ["vo_chr_110253_story/VO_CHR_110253_STORY_0042.wav"], "content": "え、なにが？", "isSys": false, "speakerIcon": "story/chara/110253_01.png", "speakerName": "オルセム", "type": "conversation"}, {"audioPaths": ["vo_chr_100001_story/VO_CHR_100001_STORY_0033.wav"], "content": "いや、きみは戦士じゃないだろう？", "isSys": false, "speakerIcon": "story/chara/100001_01.png", "speakerName": "ユーディル", "type": "conversation"}, {"audioPaths": [], "content": "魔獣退治なんて、危ないんじゃないのか？", "isSys": false, "speakerIcon": "story/chara/100001_01.png", "speakerName": "ユーディル", "type": "conversation"}, {"audioPaths": ["vo_chr_110253_story/VO_CHR_110253_STORY_0040.wav"], "content": "へーきへーき！　ってか、それなら、ユーディルもでしょ？", "isSys": false, "speakerIcon": "story/chara/110253_01.png", "speakerName": "オルセム", "type": "conversation"}, {"audioPaths": ["vo_chr_100001_story/VO_CHR_100001_STORY_0042.wav"], "content": "おれ？", "isSys": false, "speakerIcon": "story/chara/100001_01.png", "speakerName": "ユーディル", "type": "conversation"}, {"audioPaths": ["vo_chr_110253_story/VO_CHR_110253_STORY_0031.wav"], "content": "だって、きみだって王子様なんだから危ないんじゃないの？", "isSys": false, "speakerIcon": "story/chara/110253_01.png", "speakerName": "オルセム", "type": "conversation"}, {"audioPaths": ["vo_chr_100001_story/VO_CHR_100001_STORY_0035.wav"], "content": "危ないかもしれないけど、これはおれの役目だから。", "isSys": false, "speakerIcon": "story/chara/100001_01.png", "speakerName": "ユーディル", "type": "conversation"}, {"audioPaths": [], "content": "大切な国や民を守るためならなんだってやってやるさ。", "isSys": false, "speakerIcon": "story/chara/100001_01.png", "speakerName": "ユーディル", "type": "conversation"}, {"audioPaths": ["vo_chr_110253_story/VO_CHR_110253_STORY_0037.wav"], "content": "……そのためなら、自分の好きなものや夢も捨てられる？", "isSys": false, "speakerIcon": "story/chara/110253_01.png", "speakerName": "オルセム", "type": "conversation"}, {"audioPaths": ["vo_chr_100001_story/VO_CHR_100001_STORY_0043.wav"], "content": "え？　どういうこと？", "isSys": false, "speakerIcon": "story/chara/100001_01.png", "speakerName": "ユーディル", "type": "conversation"}, {"audioPaths": [], "content": "魔獣グガアアアアアア！ ", "isSys": false, "speakerIcon": "story/chara/120007_01.png", "speakerName": "魔獣", "type": "conversation"}, {"audioPaths": ["vo_chr_110253_story/VO_CHR_110253_STORY_0076.wav"], "content": "あ、やっと見つけた！よーし、いくぞ！", "isSys": false, "speakerIcon": "story/chara/110253_01.png", "speakerName": "オルセム", "type": "conversation"}, {"audioPaths": ["vo_chr_100001_story/VO_CHR_100001_STORY_0057.wav"], "content": "待て、オルセム！そんな真正面からは危ない！", "isSys": false, "speakerIcon": "story/chara/100001_01.png", "speakerName": "ユーディル", "type": "conversation"}, {"audioPaths": ["vo_chr_110253_story/VO_CHR_110253_STORY_0004.wav"], "content": "ほーらほら！オレを捕まえられるかなー？", "isSys": false, "speakerIcon": "story/chara/110253_01.png", "speakerName": "オルセム", "type": "conversation"}, {"audioPaths": ["vo_chr_100001_story/VO_CHR_100001_STORY_0017.wav"], "content": "す、すごい……。スケートで滑って魔獣をかく乱している……！", "isSys": false, "speakerIcon": "story/chara/100001_01.png", "speakerName": "ユーディル", "type": "conversation"}, {"audioPaths": ["vo_chr_110253_story/VO_CHR_110253_STORY_0055.wav"], "content": "せーのっと！", "isSys": false, "speakerIcon": "story/chara/110253_01.png", "speakerName": "オルセム", "type": "conversation"}, {"audioPaths": ["vo_chr_110253_story/VO_CHR_110253_STORY_0071.wav"], "content": "次はそこだ！", "isSys": false, "speakerIcon": "story/chara/110253_01.png", "speakerName": "オルセム", "type": "conversation"}, {"audioPaths": ["vo_chr_110253_story/VO_CHR_110253_STORY_0019.wav"], "content": "残念！オレはここだよ！", "isSys": false, "speakerIcon": "story/chara/110253_01.png", "speakerName": "オルセム", "type": "conversation"}, {"audioPaths": ["vo_chr_100001_story/VO_CHR_100001_STORY_0006.wav"], "content": "なっ、スケートで跳んで、凍った魔獣の背中に着地した!?", "isSys": false, "speakerIcon": "story/chara/100001_01.png", "speakerName": "ユーディル", "type": "conversation"}, {"audioPaths": ["vo_chr_110253_story/VO_CHR_110253_STORY_0006.wav"], "content": "着地成功！　……って、わぁ!?キミ、まだ動けたの!?", "isSys": false, "speakerIcon": "story/chara/110253_01.png", "speakerName": "オルセム", "type": "conversation"}, {"audioPaths": [], "content": "魔獣ガアアアアアゥ！ ", "isSys": false, "speakerIcon": "story/chara/120007_01.png", "speakerName": "魔獣", "type": "conversation"}, {"audioPaths": ["vo_chr_100001_story/VO_CHR_100001_STORY_0055.wav"], "content": "危ない……!!ハァァァァァッ！", "isSys": false, "speakerIcon": "story/chara/100001_01.png", "speakerName": "ユーディル", "type": "conversation"}, {"audioPaths": ["vo_chr_110253_story/VO_CHR_110253_STORY_0024.wav"], "content": "ふ～……助かったよ。ユーディル、ありがとう。", "isSys": false, "speakerIcon": "story/chara/110253_01.png", "speakerName": "オルセム", "type": "conversation"}, {"audioPaths": ["vo_chr_100001_story/VO_CHR_100001_STORY_0025.wav"], "content": "戦いの最中に油断したらダメだろ？", "isSys": false, "speakerIcon": "story/chara/100001_01.png", "speakerName": "ユーディル", "type": "conversation"}, {"audioPaths": ["vo_chr_110253_story/VO_CHR_110253_STORY_0020.wav"], "content": "あはは……ごめん。", "isSys": false, "speakerIcon": "story/chara/110253_01.png", "speakerName": "オルセム", "type": "conversation"}, {"audioPaths": ["vo_chr_100001_story/VO_CHR_100001_STORY_0017.wav"], "content": "それにしても、びっくりしたよ。あんなに戦えるなんて、思わなかった。", "isSys": false, "speakerIcon": "story/chara/100001_01.png", "speakerName": "ユーディル", "type": "conversation"}, {"audioPaths": ["vo_chr_110253_story/VO_CHR_110253_STORY_0011.wav"], "content": "……オレ、スケートをやりながらでも戦えるってのを証明したいんだ。", "isSys": false, "speakerIcon": "story/chara/110253_01.png", "speakerName": "オルセム", "type": "conversation"}, {"audioPaths": ["vo_chr_100001_story/VO_CHR_100001_STORY_0042.wav"], "content": "え……どういうこと？", "isSys": false, "speakerIcon": "story/chara/100001_01.png", "speakerName": "ユーディル", "type": "conversation"}, {"audioPaths": [], "content": "オレの故郷では、スケートが人気だったって言ったでしょ？", "isSys": false, "speakerIcon": "story/chara/110253_01.png", "speakerName": "オルセム", "type": "conversation"}, {"audioPaths": ["vo_chr_110253_story/VO_CHR_110253_STORY_0008.wav"], "content": "人気「だった」んだよ……。昔はさ。", "isSys": false, "speakerIcon": "story/chara/110253_01.png", "speakerName": "オルセム", "type": "conversation"}, {"audioPaths": ["vo_chr_110253_story/VO_CHR_110253_STORY_0023.wav"], "content": "でも毎年、魔獣が増えてきちゃって。オレの仲間はどんどん戦士になっていった……。", "isSys": false, "speakerIcon": "story/chara/110253_01.png", "speakerName": "オルセム", "type": "conversation"}, {"audioPaths": [], "content": "大好きだったはずのスケートをやめて……。", "isSys": false, "speakerIcon": "story/chara/110253_01.png", "speakerName": "オルセム", "type": "conversation"}, {"type": "break"}, {"audioPaths": ["vo_chr_110253_story/VO_CHR_110253_STORY_0034.wav"], "content": "どうしてスケートもやめなきゃいけないの!?　好きだったのに！", "isSys": false, "speakerIcon": "story/chara/110253_01.png", "speakerName": "オルセム", "type": "conversation"}, {"audioPaths": [], "content": "一緒にスケートをいろんな場所に広めようって夢はどうするのさ！", "isSys": false, "speakerIcon": "story/chara/110253_01.png", "speakerName": "オルセム", "type": "conversation"}, {"audioPaths": ["vo_chr_120013_story/VO_CHR_120013_STORY_0023.wav"], "content": "いつまでも遊んだり、夢を見てはいられないんだ。", "isSys": false, "speakerIcon": "story/chara/120013_01.png", "speakerName": "オルセムの友人", "type": "conversation"}, {"audioPaths": ["vo_chr_120013_story/VO_CHR_120013_STORY_0007.wav"], "content": "オルセム、おまえもいい加減現実を見たらどうだ。", "isSys": false, "speakerIcon": "story/chara/120013_01.png", "speakerName": "オルセムの友人", "type": "conversation"}, {"type": "break"}, {"audioPaths": ["vo_chr_110253_story/VO_CHR_110253_STORY_0038.wav"], "content": "……って、仲間に呆れられちゃったんだよね、オレ。", "isSys": false, "speakerIcon": "story/chara/110253_01.png", "speakerName": "オルセム", "type": "conversation"}, {"audioPaths": ["vo_chr_110253_story/VO_CHR_110253_STORY_0008.wav"], "content": "オレだって、故郷は大事だよ。守りたいって思う。", "isSys": false, "speakerIcon": "story/chara/110253_01.png", "speakerName": "オルセム", "type": "conversation"}, {"audioPaths": ["vo_chr_110253_story/VO_CHR_110253_STORY_0003.wav"], "content": "でも、スケートを捨てるなんてこと、オレにはできない……！", "isSys": false, "speakerIcon": "story/chara/110253_01.png", "speakerName": "オルセム", "type": "conversation"}, {"audioPaths": ["vo_chr_110253_story/VO_CHR_110253_STORY_0034.wav"], "content": "両方大事なのに片方しか選べないなんて、そんなのおかしい！", "isSys": false, "speakerIcon": "story/chara/110253_01.png", "speakerName": "オルセム", "type": "conversation"}, {"audioPaths": [], "content": "オルセム……。", "isSys": false, "speakerIcon": "story/chara/100001_01.png", "speakerName": "ユーディル", "type": "conversation"}, {"audioPaths": ["vo_chr_110253_story/VO_CHR_110253_STORY_0020.wav"], "content": "だから、スケートをしながら戦えるように猛特訓したんだ。", "isSys": false, "speakerIcon": "story/chara/110253_01.png", "speakerName": "オルセム", "type": "conversation"}, {"audioPaths": [], "content": "スケートを広めながら、少しでも魔獣を減らせるように。", "isSys": false, "speakerIcon": "story/chara/110253_01.png", "speakerName": "オルセム", "type": "conversation"}, {"audioPaths": ["vo_chr_110253_story/VO_CHR_110253_STORY_0019.wav"], "content": "それにさ、辛いときだからこそ夢は見ないと！", "isSys": false, "speakerIcon": "story/chara/110253_01.png", "speakerName": "オルセム", "type": "conversation"}, {"audioPaths": [], "content": "ねえ、ユーディル。夢を見るって、そんなに悪いこと？", "isSys": false, "speakerIcon": "story/chara/110253_01.png", "speakerName": "オルセム", "type": "conversation"}, {"audioPaths": ["vo_chr_100001_story/VO_CHR_100001_STORY_0033.wav"], "content": "いや、そんなことはないさ。おれにも夢があるんだ。", "isSys": false, "speakerIcon": "story/chara/100001_01.png", "speakerName": "ユーディル", "type": "conversation"}, {"audioPaths": [], "content": "みんなが幸せに暮らせる国を作る……って夢がね。", "isSys": false, "speakerIcon": "story/chara/100001_01.png", "speakerName": "ユーディル", "type": "conversation"}, {"audioPaths": ["vo_chr_100001_story/VO_CHR_100001_STORY_0032.wav"], "content": "だから、きみの気持ちはわかるよ。オルセム。", "isSys": false, "speakerIcon": "story/chara/100001_01.png", "speakerName": "ユーディル", "type": "conversation"}, {"audioPaths": ["vo_chr_100001_story/VO_CHR_100001_STORY_0012.wav"], "content": "どんなに辛くても、夢を叶えるために一緒に頑張ろう！", "isSys": false, "speakerIcon": "story/chara/100001_01.png", "speakerName": "ユーディル", "type": "conversation"}, {"audioPaths": ["vo_chr_110253_story/VO_CHR_110253_STORY_0012.wav"], "content": "ユーディル……。うん、約束だよ！", "isSys": false, "speakerIcon": "story/chara/110253_01.png", "speakerName": "オルセム", "type": "conversation"}], "id": 110253013, "title": "戦うスケート伝道師"}, {"conversations": [{"audioPaths": [], "content": "オルセムー！　オルセムー！いたら返事してくれ！ ", "isSys": false, "speakerIcon": "story/chara/100001_01.png", "speakerName": "ユーディル", "type": "conversation"}, {"audioPaths": ["vo_chr_100002_story/VO_CHR_100002_STORY_1039.wav"], "content": "ユーディル、見つかりましたか？", "isSys": false, "speakerIcon": null, "speakerName": "エルフィリス", "type": "conversation"}, {"audioPaths": ["vo_chr_100001_story/VO_CHR_100001_STORY_0033.wav"], "content": "いや……エルフィリスも手がかりなしみたいだな。", "isSys": false, "speakerIcon": "story/chara/100001_01.png", "speakerName": "ユーディル", "type": "conversation"}, {"audioPaths": ["vo_chr_100002_story/VO_CHR_100002_STORY_1047.wav"], "content": "はい……申し訳ありません。オルセムが行方不明になって3日……。", "isSys": false, "speakerIcon": null, "speakerName": "エルフィリス", "type": "conversation"}, {"audioPaths": ["vo_chr_100002_story/VO_CHR_100002_STORY_0008.wav"], "content": "荷物は残っていたから、出て行ったわけではないと思うのですが……。", "isSys": false, "speakerIcon": null, "speakerName": "エルフィリス", "type": "conversation"}, {"audioPaths": ["vo_chr_100001_story/VO_CHR_100001_STORY_0008.wav"], "content": "なにかに巻き込まれてなければいいけど……。", "isSys": false, "speakerIcon": "story/chara/100001_01.png", "speakerName": "ユーディル", "type": "conversation"}, {"audioPaths": ["vo_chr_120032_story/VO_CHR_120032_STORY_0004.wav"], "content": "お？　なんか金誘拐犯1持ってそうなボンボンが来やがったな。", "isSys": false, "speakerIcon": null, "speakerName": "誘拐犯1", "type": "conversation"}, {"audioPaths": ["vo_chr_120032_story/VO_CHR_120032_STORY_0012.wav"], "content": "へへっ、おまえを捕まえたら身代金をふんだくれそうだぜ！", "isSys": false, "speakerIcon": null, "speakerName": "誘拐犯1", "type": "conversation"}, {"audioPaths": ["vo_chr_100002_story/VO_CHR_100002_STORY_0038.wav"], "content": "こいつ……人さらいか。", "isSys": false, "speakerIcon": null, "speakerName": "エルフィリス", "type": "conversation"}, {"audioPaths": ["vo_chr_120032_story/VO_CHR_120032_STORY_0033.wav"], "content": "誘拐犯1人聞き悪いな。俺は街のハンターさ。獲物が、ケモノじゃないだけで。", "isSys": false, "speakerIcon": null, "speakerName": "誘拐犯1", "type": "conversation"}, {"audioPaths": ["vo_chr_120032_story/VO_CHR_120032_STORY_0004.wav"], "content": "この前はなんでも凍らせる珍しい奴も捕まえたし、ツイてるぜ。", "isSys": false, "speakerIcon": null, "speakerName": "誘拐犯1", "type": "conversation"}, {"audioPaths": ["vo_chr_100001_story/VO_CHR_100001_STORY_0002.wav"], "content": "なんでも凍らせる……？エルフィリス、もしかして……！", "isSys": false, "speakerIcon": "story/chara/100001_01.png", "speakerName": "ユーディル", "type": "conversation"}, {"audioPaths": ["vo_chr_100002_story/VO_CHR_100002_STORY_1011.wav"], "content": "オルセムの行方がわかりましたね。おい、お前！", "isSys": false, "speakerIcon": null, "speakerName": "エルフィリス", "type": "conversation"}, {"audioPaths": ["vo_chr_100002_story/VO_CHR_100002_STORY_0053.wav"], "content": "アジトの場所を吐いてもらうぞ。覚悟しろ！", "isSys": false, "speakerIcon": null, "speakerName": "エルフィリス", "type": "conversation"}, {"audioPaths": ["vo_chr_100001_story/VO_CHR_100001_STORY_0024.wav"], "content": "よし……みんな上手く忍び込めたな。", "isSys": false, "speakerIcon": "story/chara/100001_01.png", "speakerName": "ユーディル", "type": "conversation"}, {"audioPaths": ["vo_chr_100003_story/VO_CHR_100003_STORY_0011.wav"], "content": "おい、ユーディル。あそこにいたぞ。", "isSys": false, "speakerIcon": "story/chara/100003_01.png", "speakerName": "ランザーヴ", "type": "conversation"}, {"audioPaths": ["vo_chr_110253_story/VO_CHR_110253_STORY_0010.wav"], "content": "ね、キミもスケートをやってみようよ！楽しいよ！", "isSys": false, "speakerIcon": "story/chara/110253_01.png", "speakerName": "オルセム", "type": "conversation"}, {"audioPaths": [], "content": "これから一緒に、スケートを広めてくれるんでしょ？", "isSys": false, "speakerIcon": "story/chara/110253_01.png", "speakerName": "オルセム", "type": "conversation"}, {"audioPaths": ["vo_chr_110253_story/VO_CHR_110253_STORY_0031.wav"], "content": "それなら、まずキミたちがスケートの楽しさを知らないと！", "isSys": false, "speakerIcon": "story/chara/110253_01.png", "speakerName": "オルセム", "type": "conversation"}, {"audioPaths": ["vo_chr_120033_story/VO_CHR_120033_STORY_0025.wav"], "content": "あー、わかったわかった。ヒマができたら、付き合ってやるよ。", "isSys": false, "speakerIcon": "story/chara/120033_01.png", "speakerName": "誘拐犯2", "type": "conversation"}, {"audioPaths": [], "content": "チッ……能力は珍しいのにウザったい奴だ。", "isSys": false, "speakerIcon": "story/chara/120033_01.png", "speakerName": "誘拐犯2", "type": "conversation"}, {"audioPaths": ["vo_chr_120043_story/VO_CHR_120043_STORY_0004.wav"], "content": "さっさとどこかに売り飛ばしちまおうぜ。", "isSys": false, "speakerIcon": "story/chara/120043_01.png", "speakerName": "誘拐犯3", "type": "conversation"}, {"audioPaths": ["vo_chr_100004_story/VO_CHR_100004_STORY_0023.wav"], "content": "オルセムさん……誘拐されたわりには元気ですね。", "isSys": false, "speakerIcon": "story/chara/100004_01.png", "speakerName": "クラウ", "type": "conversation"}, {"audioPaths": ["vo_chr_100003_story/VO_CHR_100003_STORY_0025.wav"], "content": "一緒にスケートを広めてやるって言われてついて行っちまったんだろ。", "isSys": false, "speakerIcon": "story/chara/100003_01.png", "speakerName": "ランザーヴ", "type": "conversation"}, {"audioPaths": ["vo_chr_100002_story/VO_CHR_100002_STORY_0037.wav"], "content": "だまされていると気づいてないのか？まったく、なんてお人よしだ……。", "isSys": false, "speakerIcon": null, "speakerName": "エルフィリス", "type": "conversation"}, {"audioPaths": ["vo_chr_100001_story/VO_CHR_100001_STORY_0020.wav"], "content": "ま、まあ……無事だったんだから。それじゃ、助けに行くぞ！", "isSys": false, "speakerIcon": "story/chara/100001_01.png", "speakerName": "ユーディル", "type": "conversation"}, {"audioPaths": ["vo_chr_100002_story/VO_CHR_100002_STORY_0053.wav"], "content": "誘拐犯ども、そこまでだ！", "isSys": false, "speakerIcon": null, "speakerName": "エルフィリス", "type": "conversation"}, {"audioPaths": ["vo_chr_120033_story/VO_CHR_120033_STORY_0006.wav"], "content": "なっ、なんだお前らは……！", "isSys": false, "speakerIcon": "story/chara/120033_01.png", "speakerName": "誘拐犯2", "type": "conversation"}, {"audioPaths": ["vo_chr_120033_story/VO_CHR_120033_STORY_0056.wav"], "content": "ぐあっ！", "isSys": false, "speakerIcon": "story/chara/120033_01.png", "speakerName": "誘拐犯2", "type": "conversation"}, {"audioPaths": ["vo_chr_100001_story/VO_CHR_100001_STORY_0050.wav"], "content": "オルセム、大丈夫か!?", "isSys": false, "speakerIcon": "story/chara/100001_01.png", "speakerName": "ユーディル", "type": "conversation"}, {"audioPaths": ["vo_chr_110253_story/VO_CHR_110253_STORY_0042.wav"], "content": "え？　ユーディル？どうしてここに……。", "isSys": false, "speakerIcon": "story/chara/110253_01.png", "speakerName": "オルセム", "type": "conversation"}, {"audioPaths": ["vo_chr_100001_story/VO_CHR_100001_STORY_0038.wav"], "content": "きみはだまされてる！　こいつらはきみの夢を手伝う気なんてない！", "isSys": false, "speakerIcon": "story/chara/100001_01.png", "speakerName": "ユーディル", "type": "conversation"}, {"audioPaths": ["vo_chr_100001_story/VO_CHR_100001_STORY_0031.wav"], "content": "こいつらはきみの能力を売ろうとしてる悪い奴なんだ！", "isSys": false, "speakerIcon": "story/chara/100001_01.png", "speakerName": "ユーディル", "type": "conversation"}, {"audioPaths": ["vo_chr_110253_story/VO_CHR_110253_STORY_0006.wav"], "content": "え……嘘だったの？　スケート一緒に広めてくれるんじゃなかったの？", "isSys": false, "speakerIcon": "story/chara/110253_01.png", "speakerName": "オルセム", "type": "conversation"}, {"audioPaths": ["vo_chr_120043_story/VO_CHR_120043_STORY_0034.wav"], "content": "うるせぇ！　そんなのはどうでもいい！大事なのはお前の能力だ！", "isSys": false, "speakerIcon": "story/chara/120043_01.png", "speakerName": "誘拐犯3", "type": "conversation"}, {"audioPaths": [], "content": "だからお前に逃げられたら困るんだよ！　どけ！", "isSys": false, "speakerIcon": "story/chara/120043_01.png", "speakerName": "誘拐犯3", "type": "conversation"}, {"audioPaths": ["vo_chr_100001_story/VO_CHR_100001_STORY_0071.wav"], "content": "させるか！　オルセム！　とりあえず、きみはここから逃げるんだ！", "isSys": false, "speakerIcon": "story/chara/100001_01.png", "speakerName": "ユーディル", "type": "conversation"}, {"audioPaths": ["vo_chr_110253_story/VO_CHR_110253_STORY_0003.wav"], "content": "そう……嘘、だったんだ……。はは…………。", "isSys": false, "speakerIcon": "story/chara/110253_01.png", "speakerName": "オルセム", "type": "conversation"}, {"audioPaths": ["vo_chr_100001_story/VO_CHR_100001_STORY_0042.wav", "vo_chr_100001_story/VO_CHR_100001_STORY_1002.wav"], "content": "オルセム……？急に寒く……って、床が凍ってる!?", "isSys": false, "speakerIcon": "story/chara/100001_01.png", "speakerName": "ユーディル", "type": "conversation"}, {"audioPaths": [], "content": "だまされたオレも悪いけど……でも、さすがにこれは許せないよ。", "isSys": false, "speakerIcon": "story/chara/110253_01.png", "speakerName": "オルセム", "type": "conversation"}, {"audioPaths": ["vo_chr_110253_story/VO_CHR_110253_STORY_0002.wav"], "content": "スケートを……オレの夢を利用しようとしたってことは、絶対にね！", "isSys": false, "speakerIcon": "story/chara/110253_01.png", "speakerName": "オルセム", "type": "conversation"}, {"audioPaths": ["vo_chr_120043_story/VO_CHR_120043_STORY_0006.wav"], "content": "なんだ、こいつ！すごいスピードで……くそっ！", "isSys": false, "speakerIcon": "story/chara/120043_01.png", "speakerName": "誘拐犯3", "type": "conversation"}, {"audioPaths": ["vo_chr_120036_story/VO_CHR_120036_STORY_0054.wav"], "content": "お、おい、逃げるな……誘拐犯4うわッ！ ", "isSys": false, "speakerIcon": "story/chara/120036_01.png", "speakerName": "誘拐犯4", "type": "conversation"}, {"audioPaths": ["vo_chr_100001_story/VO_CHR_100001_STORY_0017.wav"], "content": "すごい……アジトの中を高速で滑って……！", "isSys": false, "speakerIcon": "story/chara/100001_01.png", "speakerName": "ユーディル", "type": "conversation"}, {"audioPaths": ["vo_chr_100003_story/VO_CHR_100003_STORY_0037.wav"], "content": "あんなん、目で追えねぇぞ！", "isSys": false, "speakerIcon": "story/chara/100003_01.png", "speakerName": "ランザーヴ", "type": "conversation"}, {"audioPaths": ["vo_chr_110253_story/VO_CHR_110253_STORY_0055.wav"], "content": "キミで最後だ！", "isSys": false, "speakerIcon": "story/chara/110253_01.png", "speakerName": "オルセム", "type": "conversation"}, {"audioPaths": ["vo_chr_120043_story/VO_CHR_120043_STORY_0056.wav"], "content": "うわああっ！", "isSys": false, "speakerIcon": "story/chara/120043_01.png", "speakerName": "誘拐犯3", "type": "conversation"}, {"audioPaths": ["vo_chr_100004_story/VO_CHR_100004_STORY_0024.wav"], "content": "……一件落着ですね。オルセムさん、ケガはありませんか？", "isSys": false, "speakerIcon": "story/chara/100004_01.png", "speakerName": "クラウ", "type": "conversation"}, {"audioPaths": ["vo_chr_110253_story/VO_CHR_110253_STORY_0011.wav"], "content": "クラウ……うん、オレは平気だよ。", "isSys": false, "speakerIcon": "story/chara/110253_01.png", "speakerName": "オルセム", "type": "conversation"}, {"audioPaths": ["vo_chr_100004_story/VO_CHR_100004_STORY_0021.wav"], "content": "それならよかった。まったく……心配しましたよ。", "isSys": false, "speakerIcon": "story/chara/100004_01.png", "speakerName": "クラウ", "type": "conversation"}, {"audioPaths": ["vo_chr_100002_story/VO_CHR_100002_STORY_0032.wav"], "content": "そうだぞ、オルセム。", "isSys": false, "speakerIcon": null, "speakerName": "エルフィリス", "type": "conversation"}, {"audioPaths": ["vo_chr_100002_story/VO_CHR_100002_STORY_0025.wav"], "content": "夢に一生懸命になるのはいいが、お前はもう少し周りを見ろ。", "isSys": false, "speakerIcon": null, "speakerName": "エルフィリス", "type": "conversation"}, {"audioPaths": ["vo_chr_110253_story/VO_CHR_110253_STORY_0038.wav"], "content": "あ……うん。そうだね。反省する……。心配かけて、ごめんなさい。", "isSys": false, "speakerIcon": "story/chara/110253_01.png", "speakerName": "オルセム", "type": "conversation"}, {"audioPaths": ["vo_chr_110253_story/VO_CHR_110253_STORY_0048.wav"], "content": "オレ、みんなになんて言ったら……。本当に……ごめんなさい。", "isSys": false, "speakerIcon": "story/chara/110253_01.png", "speakerName": "オルセム", "type": "conversation"}, {"audioPaths": ["vo_chr_100003_story/VO_CHR_100003_STORY_0030.wav"], "content": "ま、無事でよかったよ。他の被害者もケガはなさそうだ。", "isSys": false, "speakerIcon": "story/chara/100003_01.png", "speakerName": "ランザーヴ", "type": "conversation"}, {"audioPaths": ["vo_chr_100003_story/VO_CHR_100003_STORY_0001.wav"], "content": "みんなを解放して、おれたちも城に帰ろうぜ。", "isSys": false, "speakerIcon": "story/chara/100003_01.png", "speakerName": "ランザーヴ", "type": "conversation"}, {"audioPaths": ["vo_chr_110253_story/VO_CHR_110253_STORY_0011.wav"], "content": "え……あ、ああ……。帰ろうか……うん。", "isSys": false, "speakerIcon": "story/chara/110253_01.png", "speakerName": "オルセム", "type": "conversation"}, {"audioPaths": ["vo_chr_110253_story/VO_CHR_110253_STORY_0023.wav"], "content": "でも……オレ、帰っていいのかな……。", "isSys": false, "speakerIcon": "story/chara/110253_01.png", "speakerName": "オルセム", "type": "conversation"}, {"audioPaths": ["vo_chr_100001_story/VO_CHR_100001_STORY_0042.wav"], "content": "オルセム……？", "isSys": false, "speakerIcon": "story/chara/100001_01.png", "speakerName": "ユーディル", "type": "conversation"}], "id": 110253014, "title": "囚われのスケート伝道師"}, {"conversations": [{"audioPaths": ["vo_chr_110253_story/VO_CHR_110253_STORY_0003.wav"], "content": "このほうがいいんだよね……。オレは、この城を出ていったほうが……。", "isSys": false, "speakerIcon": "story/chara/110253_01.png", "speakerName": "オルセム", "type": "conversation"}, {"audioPaths": [], "content": "ユーディル、ありがとう。バイバイ。", "isSys": false, "speakerIcon": "story/chara/110253_01.png", "speakerName": "オルセム", "type": "conversation"}, {"audioPaths": ["vo_chr_100001_story/VO_CHR_100001_STORY_0054.wav"], "content": "オルセムー！待ってくれ、オルセム！", "isSys": false, "speakerIcon": null, "speakerName": "ユーディル", "type": "conversation"}, {"audioPaths": ["vo_chr_110253_story/VO_CHR_110253_STORY_0006.wav"], "content": "え!?　ユーディル？どうして……。", "isSys": false, "speakerIcon": "story/chara/110253_01.png", "speakerName": "オルセム", "type": "conversation"}, {"audioPaths": ["vo_chr_100001_story/VO_CHR_100001_STORY_0026.wav"], "content": "はあ……はあ……間に合ってよかった。", "isSys": false, "speakerIcon": null, "speakerName": "ユーディル", "type": "conversation"}, {"audioPaths": [], "content": "オルセム、この書置きはなんだ？急に故郷に帰るって……。", "isSys": false, "speakerIcon": null, "speakerName": "ユーディル", "type": "conversation"}, {"audioPaths": ["vo_chr_110253_story/VO_CHR_110253_STORY_0062.wav"], "content": "オレが城にいても、みんなの迷惑になるからさ……。", "isSys": false, "speakerIcon": "story/chara/110253_01.png", "speakerName": "オルセム", "type": "conversation"}, {"audioPaths": ["vo_chr_110253_story/VO_CHR_110253_STORY_0023.wav"], "content": "この間だって、悪いヤツらにまんまと乗せられて、手間かけちゃったし。", "isSys": false, "speakerIcon": "story/chara/110253_01.png", "speakerName": "オルセム", "type": "conversation"}, {"audioPaths": [], "content": "それに、結局……故郷を離れても同じだったから。", "isSys": false, "speakerIcon": "story/chara/110253_01.png", "speakerName": "オルセム", "type": "conversation"}, {"audioPaths": ["vo_chr_100001_story/VO_CHR_100001_STORY_0042.wav"], "content": "同じ？", "isSys": false, "speakerIcon": null, "speakerName": "ユーディル", "type": "conversation"}, {"type": "break"}, {"audioPaths": ["vo_chr_100002_story/VO_CHR_100002_STORY_0025.wav"], "content": "夢に一生懸命になるのはいいが、お前はもう少し周りを見ろ。", "isSys": false, "speakerIcon": "story/chara/100002_01.png", "speakerName": "エルフィリス", "type": "conversation"}, {"type": "break"}, {"audioPaths": ["vo_chr_120013_story/VO_CHR_120013_STORY_0007.wav"], "content": "オルセム、お前もいい加減現実を見たらどうだ。", "isSys": false, "speakerIcon": "story/chara/120013_01.png", "speakerName": "オルセムの友人", "type": "conversation"}, {"type": "break"}, {"audioPaths": ["vo_chr_110253_story/VO_CHR_110253_STORY_0003.wav"], "content": "落ち着いて周りを見て、わかったんだ。夢って、結局夢なんだよね。", "isSys": false, "speakerIcon": "story/chara/110253_01.png", "speakerName": "オルセム", "type": "conversation"}, {"audioPaths": ["vo_chr_110253_story/VO_CHR_110253_STORY_0020.wav"], "content": "だからオレも、スケートのことは忘れて故郷で戦士になろうかなって。", "isSys": false, "speakerIcon": "story/chara/110253_01.png", "speakerName": "オルセム", "type": "conversation"}, {"audioPaths": ["vo_chr_110253_story/VO_CHR_110253_STORY_0023.wav"], "content": "どんなに頑張っても、叶わないんだからさ……。", "isSys": false, "speakerIcon": "story/chara/110253_01.png", "speakerName": "オルセム", "type": "conversation"}, {"audioPaths": ["vo_chr_100001_story/VO_CHR_100001_STORY_0035.wav"], "content": "おれはそう思わないけどな。ほら、後ろを見て。", "isSys": false, "speakerIcon": null, "speakerName": "ユーディル", "type": "conversation"}, {"audioPaths": ["vo_chr_110253_story/VO_CHR_110253_STORY_0037.wav"], "content": "え……？", "isSys": false, "speakerIcon": "story/chara/110253_01.png", "speakerName": "オルセム", "type": "conversation"}, {"audioPaths": ["vo_chr_120016_story/VO_CHR_120016_STORY_0017.wav"], "content": "あ！　スケートのお兄ちゃんだ！", "isSys": false, "speakerIcon": "story/chara/120016_01.png", "speakerName": "女の子", "type": "conversation"}, {"audioPaths": ["vo_chr_120019_story/VO_CHR_120019_STORY_0010.wav"], "content": "男性兄ちゃん、もう一度、あの氷の上を滑るやつ見せてくれよ！", "isSys": false, "speakerIcon": "story/chara/120019_01.png", "speakerName": "男性", "type": "conversation"}, {"audioPaths": ["vo_chr_120018_story/VO_CHR_120018_STORY_0016.wav"], "content": "女性1私もあれ、やってみたい！", "isSys": false, "speakerIcon": "story/chara/120018_01.png", "speakerName": "女性1", "type": "conversation"}, {"audioPaths": ["vo_chr_100001_story/VO_CHR_100001_STORY_1001.wav"], "content": "きみのスケートに、興味を持った人もいるみたいだよ。", "isSys": false, "speakerIcon": null, "speakerName": "ユーディル", "type": "conversation"}, {"audioPaths": ["vo_chr_120017_story/VO_CHR_120017_STORY_0046.wav"], "content": "お兄ちゃん！この前は助けてくれて、ありがとう！", "isSys": false, "speakerIcon": "story/chara/120038_01.png", "speakerName": "男の子", "type": "conversation"}, {"audioPaths": ["vo_chr_110253_story/VO_CHR_110253_STORY_0007.wav"], "content": "あ、キミ……オレと一緒に捕まってた……。", "isSys": false, "speakerIcon": "story/chara/110253_01.png", "speakerName": "オルセム", "type": "conversation"}, {"audioPaths": ["vo_chr_120017_story/VO_CHR_120017_STORY_0017.wav"], "content": "お兄ちゃん、すっげーカッコよかった！男の子氷の上を滑ってガーってやっつけて！", "isSys": false, "speakerIcon": "story/chara/120038_01.png", "speakerName": "男の子", "type": "conversation"}, {"audioPaths": ["vo_chr_120018_story/VO_CHR_120018_STORY_0046.wav"], "content": "あなたが明るく振舞っていたから、捕まっていた私たちも救われてました。", "isSys": false, "speakerIcon": "story/chara/120012_01.png", "speakerName": "女性2", "type": "conversation"}, {"audioPaths": ["vo_chr_120017_story/VO_CHR_120017_STORY_0004.wav"], "content": "ねえ！　ボクもあれやりたい！教えて教えて！", "isSys": false, "speakerIcon": "story/chara/120038_01.png", "speakerName": "男の子", "type": "conversation"}, {"audioPaths": ["vo_chr_110253_story/VO_CHR_110253_STORY_0003.wav"], "content": "みんな……。", "isSys": false, "speakerIcon": "story/chara/110253_01.png", "speakerName": "オルセム", "type": "conversation"}, {"audioPaths": ["vo_chr_100001_story/VO_CHR_100001_STORY_0030.wav"], "content": "……オルセム、エルフィリスが「周りを見ろ」って言ったのは非難じゃないよ。", "isSys": false, "speakerIcon": null, "speakerName": "ユーディル", "type": "conversation"}, {"audioPaths": ["vo_chr_100001_story/VO_CHR_100001_STORY_0033.wav"], "content": "現実を見ろって意味もあったと思うけど、それだけじゃない。", "isSys": false, "speakerIcon": null, "speakerName": "ユーディル", "type": "conversation"}, {"audioPaths": [], "content": "きみがまっすぐだから、周りを見ないと自分が傷つくって心配したんだと思う。", "isSys": false, "speakerIcon": null, "speakerName": "ユーディル", "type": "conversation"}, {"audioPaths": ["vo_chr_110253_story/VO_CHR_110253_STORY_0008.wav"], "content": "それって、さらわれたときみたいに……？", "isSys": false, "speakerIcon": "story/chara/110253_01.png", "speakerName": "オルセム", "type": "conversation"}, {"audioPaths": ["vo_chr_100001_story/VO_CHR_100001_STORY_0032.wav"], "content": "ああ。オルセム、きみの夢は少しずつ叶っているよ。", "isSys": false, "speakerIcon": null, "speakerName": "ユーディル", "type": "conversation"}, {"audioPaths": [], "content": "だから、焦ってがむしゃらに突き進む必要はないんだ。", "isSys": false, "speakerIcon": null, "speakerName": "ユーディル", "type": "conversation"}, {"audioPaths": ["vo_chr_100001_story/VO_CHR_100001_STORY_1001.wav"], "content": "きみの周りにはもう、スケートの虜になってる人がいるんだからさ。", "isSys": false, "speakerIcon": null, "speakerName": "ユーディル", "type": "conversation"}, {"audioPaths": [], "content": "ほら、もっとよく周りを見てごらん。", "isSys": false, "speakerIcon": null, "speakerName": "ユーディル", "type": "conversation"}, {"audioPaths": ["vo_chr_110253_story/VO_CHR_110253_STORY_0023.wav"], "content": "……そうか。オレ、夢を叶えたくて、焦って、周りが見えてなかったんだね。", "isSys": false, "speakerIcon": "story/chara/110253_01.png", "speakerName": "オルセム", "type": "conversation"}, {"audioPaths": ["vo_chr_110253_story/VO_CHR_110253_STORY_0073.wav"], "content": "こんなに、スケートに興味を持ってくれた人がいるのに……。", "isSys": false, "speakerIcon": "story/chara/110253_01.png", "speakerName": "オルセム", "type": "conversation"}, {"audioPaths": ["vo_chr_100001_story/VO_CHR_100001_STORY_0030.wav"], "content": "オルセム、おれは兄上たちみたいに影響力のある王子じゃない。", "isSys": false, "speakerIcon": null, "speakerName": "ユーディル", "type": "conversation"}, {"audioPaths": [], "content": "でも、仲間として、きみの夢が叶うように手伝いたいって思うよ。", "isSys": false, "speakerIcon": null, "speakerName": "ユーディル", "type": "conversation"}, {"audioPaths": ["vo_chr_100001_story/VO_CHR_100001_STORY_0040.wav"], "content": "諦めないで、一緒に夢を叶えていこう。", "isSys": false, "speakerIcon": null, "speakerName": "ユーディル", "type": "conversation"}, {"audioPaths": ["vo_chr_110253_story/VO_CHR_110253_STORY_0020.wav"], "content": "ユーディル……！あはは、オレ、本当にバカだな……。", "isSys": false, "speakerIcon": "story/chara/110253_01.png", "speakerName": "オルセム", "type": "conversation"}, {"audioPaths": ["vo_chr_110253_story/VO_CHR_110253_STORY_0024.wav"], "content": "もう独りじゃないってことに、今まで気づいてなかったなんて……。", "isSys": false, "speakerIcon": "story/chara/110253_01.png", "speakerName": "オルセム", "type": "conversation"}, {"audioPaths": ["vo_chr_110253_story/VO_CHR_110253_STORY_0012.wav"], "content": "こうしちゃいられない！　みんなにスケートの魅力をたくさん伝えないと！", "isSys": false, "speakerIcon": "story/chara/110253_01.png", "speakerName": "オルセム", "type": "conversation"}, {"audioPaths": [], "content": "こんなに人が集まったなら、たくさんブレードが必要だね！", "isSys": false, "speakerIcon": "story/chara/110253_01.png", "speakerName": "オルセム", "type": "conversation"}, {"audioPaths": ["vo_chr_110253_story/VO_CHR_110253_STORY_0071.wav"], "content": "ちょっとオレ、とってくる！先に中庭に行っててー！", "isSys": false, "speakerIcon": "story/chara/110253_01.png", "speakerName": "オルセム", "type": "conversation"}, {"audioPaths": ["vo_chr_110253_story/VO_CHR_110253_STORY_0072.wav"], "content": "じゃじゃーん！スケート講座、はっじまっるよー！", "isSys": false, "speakerIcon": "story/chara/110253_01.png", "speakerName": "オルセム", "type": "conversation"}, {"audioPaths": [], "content": "まずは、ブレードをつけた靴で地面に立って……。", "isSys": false, "speakerIcon": "story/chara/110253_01.png", "speakerName": "オルセム", "type": "conversation"}, {"audioPaths": ["vo_chr_110253_story/VO_CHR_110253_STORY_0012.wav"], "content": "そう！　そのまま足を交互に出すんだ！せーの、右！　左！　右！　左！ ", "isSys": false, "speakerIcon": "story/chara/110253_01.png", "speakerName": "オルセム", "type": "conversation"}, {"audioPaths": ["vo_chr_100003_story/VO_CHR_100003_STORY_0016.wav"], "content": "説明、上手くなったじゃねぇか。", "isSys": false, "speakerIcon": "story/chara/100003_01.png", "speakerName": "ランザーヴ", "type": "conversation"}, {"audioPaths": ["vo_chr_100004_story/VO_CHR_100004_STORY_0019.wav"], "content": "まだ勢いで説明しているところもありますけどね。", "isSys": false, "speakerIcon": "story/chara/100004_01.png", "speakerName": "クラウ", "type": "conversation"}, {"audioPaths": ["vo_chr_100002_story/VO_CHR_100002_STORY_0012.wav"], "content": "それにしても、みんないい笑顔だな。オルセムも楽しそうでよかった。", "isSys": false, "speakerIcon": "story/chara/100002_01.png", "speakerName": "エルフィリス", "type": "conversation"}, {"audioPaths": ["vo_chr_110253_story/VO_CHR_110253_STORY_0010.wav"], "content": "みんなー！　そんなところで見てないで、一緒に滑ろう！", "isSys": false, "speakerIcon": "story/chara/110253_01.png", "speakerName": "オルセム", "type": "conversation"}, {"audioPaths": ["vo_chr_100001_story/VO_CHR_100001_STORY_0012.wav"], "content": "ああ！　今、行くよ！", "isSys": false, "speakerIcon": null, "speakerName": "ユーディル", "type": "conversation"}, {"audioPaths": ["vo_chr_110253_story/VO_CHR_110253_STORY_0017.wav"], "content": "わ！　ユーディル、上手く滑れるようになったね。", "isSys": false, "speakerIcon": "story/chara/110253_01.png", "speakerName": "オルセム", "type": "conversation"}, {"audioPaths": ["vo_chr_110253_story/VO_CHR_110253_STORY_0011.wav"], "content": "……オレ、一緒に夢を叶えてくれる仲間ができて、すごく嬉しかったんだ。", "isSys": false, "speakerIcon": "story/chara/110253_01.png", "speakerName": "オルセム", "type": "conversation"}, {"audioPaths": [], "content": "だから今度はオレの番！オレもキミの夢を叶えるのを手伝う！", "isSys": false, "speakerIcon": "story/chara/110253_01.png", "speakerName": "オルセム", "type": "conversation"}, {"audioPaths": ["vo_chr_110253_story/VO_CHR_110253_STORY_0001.wav"], "content": "みんなで一緒に夢を追おう！", "isSys": false, "speakerIcon": "story/chara/110253_01.png", "speakerName": "オルセム", "type": "conversation"}, {"audioPaths": ["vo_chr_100001_story/VO_CHR_100001_STORY_0012.wav"], "content": "ああ、ありがとう、オルセム。これからもよろしくな！", "isSys": false, "speakerIcon": null, "speakerName": "ユーディル", "type": "conversation"}], "id": 110253015, "title": "スケート伝道師の夢"}]